[
{
"asset_id":
"d761afc0-aa3d-4ed3-a490-58d866c195e2",
"blob":
"f6db2ca2-1542-4109-90cc-af97c2e8da7b",
"created":
"2023-05-19T20:33:18.455831+00:00",
"metadata":
{
"@context":
"https://raw.githubusercontent.com/dandi/schema/master/releases/0.6.4/context.json",
"access":
[
{
"schemaKey":
"AccessRequirements",
"status":
"dandi:OpenAccess"
}
],
"approach":
[],
"blobDateModified":
"2023-05-19T15:42:10.161263-04:00",
"contentSize":
1865870123,
"contentUrl":
[
"https://api.dandiarchive.org/api/assets/d761afc0-aa3d-4ed3-a490-58d866c195e2/download/",
"https://dandiarchive.s3.amazonaws.com/blobs/f6d/b2c/f6db2ca2-1542-4109-90cc-af97c2e8da7b"
],
"dateModified":
"2023-05-19T16:31:04.086238-04:00",
"datePublished":
"2023-05-19T20:43:22.827243+00:00",
"digest":
{
"dandi:dandi-etag":
"39d4d47a93e24d114e6e3be5c4a3c818-28",
"dandi:sha2-256":
"98e7407cd97a9914948ebbd528044e48f4f5efe4220538c2b78a69fba7eeb3f6"
},
"encodingFormat":
"application/x-nwb",
"id":
"dandiasset:d761afc0-aa3d-4ed3-a490-58d866c195e2",
"identifier":
"d761afc0-aa3d-4ed3-a490-58d866c195e2",
"measurementTechnique":
[],
"path":
"sub-Fig4-5-Bi100us-09/sub-Fig4-5-Bi100us-09_ses-BPAE-5xBipolar-100us_image.nwb",
"publishedBy":
{
"endDate":
"2023-05-19T20:43:22.827243+00:00",
"id":
"urn:uuid:77bfdbaa-7fcd-4379-bb75-a7fa70f0a20e",
"name":
"DANDI publish",
"schemaKey":
"PublishActivity",
"startDate":
"2023-05-19T20:43:22.827243+00:00",
"wasAssociatedWith":
[
{
"id":
"urn:uuid:6861084b-d891-4a52-8359-1454cab37032",
"identifier":
"RRID:SCR_017571",
"name":
"DANDI API",
"schemaKey":
"Software",
"version":
"0.1.0"
}
]
},
"schemaKey":
"Asset",
"schemaVersion":
"0.6.4",
"variableMeasured":
[],
"wasAttributedTo":
[
{
"age":
{
"schemaKey":
"PropertyValue",
"unitText":
"ISO-8601 duration",
"value":
"P1D",
"valueReference":
{
"schemaKey":
"PropertyValue",
"value":
"dandi:BirthReference"
}
},
"identifier":
"Fig4_5_Bi100us_09",
"schemaKey":
"Participant",
"sex":
{
"name":
"Unknown",
"schemaKey":
"SexType"
},
"species":
{
"identifier":
"http://purl.obolibrary.org/obo/NCBITaxon_9913",
"name":
"Bos taurus - Cattle",
"schemaKey":
"SpeciesType"
}
}
],
"wasGeneratedBy":
[
{
"description":
"Cells were electroporated by a train of 5 100+100 us bipolar pulses (amplitude of the second phase was 50% the first phase's amplitude) at 1 Hz.The electrodes were two parallel stainless-steel cylinders, 1.5 mm in diameter and 3 mm apart",
"identifier":
"BPAE_5xBipolar_100us",
"name":
"BPAE_5xBipolar_100us",
"schemaKey":
"Session",
"startDate":
"2021-11-20T20:04:08-05:00"
},
{
"description":
"Metadata generated by DANDI cli",
"endDate":
"2023-05-19T16:31:04.086238-04:00",
"id":
"urn:uuid:858d08ff-a9d5-4b44-b44c-ca5cc7769200",
"name":
"Metadata generation",
"schemaKey":
"Activity",
"startDate":
"2023-05-19T16:31:04.019941-04:00",
"wasAssociatedWith":
[
{
"identifier":
"RRID:SCR_019009",
"name":
"DANDI Command Line Interface",
"schemaKey":
"Software",
"url":
"https://github.com/dandi/dandi-cli",
"version":
"0.55.0"
}
]
}
]
},
"modified":
"2023-05-19T20:43:22.828771+00:00",
"path":
"sub-Fig4-5-Bi100us-09/sub-Fig4-5-Bi100us-09_ses-BPAE-5xBipolar-100us_image.nwb",
"size":
1865870123
},
{
"asset_id":
"7e033d40-2d51-4e18-a007-d9a5ea1852b0",
"blob":
"c9774bfc-3b68-4ce9-bf7d-e064229eaf4e",
"created":
"2023-05-19T20:33:30.769920+00:00",
"metadata":
{
"@context":
"https://raw.githubusercontent.com/dandi/schema/master/releases/0.6.4/context.json",
"access":
[
{
"schemaKey":
"AccessRequirements",
"status":
"dandi:OpenAccess"
}
],
"approach":
[],
"blobDateModified":
"2023-05-19T15:49:09.567280-04:00",
"contentSize":
1881747900,
"contentUrl":
[
"https://api.dandiarchive.org/api/assets/7e033d40-2d51-4e18-a007-d9a5ea1852b0/download/",
"https://dandiarchive.s3.amazonaws.com/blobs/c97/74b/c9774bfc-3b68-4ce9-bf7d-e064229eaf4e"
],
"dateModified":
"2023-05-19T16:31:05.402974-04:00",
"datePublished":
"2023-05-19T20:43:22.818369+00:00",
"digest":
{
"dandi:dandi-etag":
"4a7d51485c30efbd70807b8ed01c0a2b-29",
"dandi:sha2-256":
"56d124dc6e0cd75311d628656455b0e62694508a3dcb98e0cfdd7e174c6ce2ba"
},
"encodingFormat":
"application/x-nwb",
"id":
"dandiasset:7e033d40-2d51-4e18-a007-d9a5ea1852b0",
"identifier":
"7e033d40-2d51-4e18-a007-d9a5ea1852b0",
"measurementTechnique":
[],
"path":
"sub-Fig4-5-Bi100us-11/sub-Fig4-5-Bi100us-11_ses-BPAE-5xBipolar-100us_image.nwb",
"publishedBy":
{
"endDate":
"2023-05-19T20:43:22.818369+00:00",
"id":
"urn:uuid:2d49fdc0-66a2-4389-a912-62a1d1fb2823",
"name":
"DANDI publish",
"schemaKey":
"PublishActivity",
"startDate":
"2023-05-19T20:43:22.818369+00:00",
"wasAssociatedWith":
[
{
"id":
"urn:uuid:a451326d-31df-4e4b-9ef4-69f719687e6e",
"identifier":
"RRID:SCR_017571",
"name":
"DANDI API",
"schemaKey":
"Software",
"version":
"0.1.0"
}
]
},
"schemaKey":
"Asset",
"schemaVersion":
"0.6.4",
"variableMeasured":
[],
"wasAttributedTo":
[
{
"age":
{
"schemaKey":
"PropertyValue",
"unitText":
"ISO-8601 duration",
"value":
"P1D",
"valueReference":
{
"schemaKey":
"PropertyValue",
"value":
"dandi:BirthReference"
}
},
"identifier":
"Fig4_5_Bi100us_11",
"schemaKey":
"Participant",
"sex":
{
"name":
"Unknown",
"schemaKey":
"SexType"
},
"species":
{
"identifier":
"http://purl.obolibrary.org/obo/NCBITaxon_9913",
"name":
"Bos taurus - Cattle",
"schemaKey":
"SpeciesType"
}
}
],
"wasGeneratedBy":
[
{
"description":
"Cells were electroporated by a train of 5 100+100 us bipolar pulses (amplitude of the second phase was 50% the first phase's amplitude) at 1 Hz.The electrodes were two parallel stainless-steel cylinders, 1.5 mm in diameter and 3 mm apart",
"identifier":
"BPAE_5xBipolar_100us",
"name":
"BPAE_5xBipolar_100us",
"schemaKey":
"Session",
"startDate":
"2021-11-20T22:28:16-05:00"
},
{
"description":
"Metadata generated by DANDI cli",
"endDate":
"2023-05-19T16:31:05.402974-04:00",
"id":
"urn:uuid:f6b0e5b9-50be-432d-b057-b5e60a7e26a3",
"name":
"Metadata generation",
"schemaKey":
"Activity",
"startDate":
"2023-05-19T16:31:05.287931-04:00",
"wasAssociatedWith":
[
{
"identifier":
"RRID:SCR_019009",
"name":
"DANDI Command Line Interface",
"schemaKey":
"Software",
"url":
"https://github.com/dandi/dandi-cli",
"version":
"0.55.0"
}
]
}
]
},
"modified":
"2023-05-19T20:43:22.820122+00:00",
"path":
"sub-Fig4-5-Bi100us-11/sub-Fig4-5-Bi100us-11_ses-BPAE-5xBipolar-100us_image.nwb",
"size":
1881747900
},
{
"asset_id":
"05acd77d-8307-4def-9b53-bda11a1177d5",
"blob":
"4988917d-8182-4bd8-9e38-dd38c94c08fa",
"created":
"2023-05-19T20:33:33.001410+00:00",
"metadata":
{
"@context":
"https://raw.githubusercontent.com/dandi/schema/master/releases/0.6.4/context.json",
"access":
[
{
"schemaKey":
"AccessRequirements",
"status":
"dandi:OpenAccess"
}
],
"approach":
[],
"blobDateModified":
"2023-05-19T15:52:23.697530-04:00",
"contentSize":
1871663171,
"contentUrl":
[
"https://api.dandiarchive.org/api/assets/05acd77d-8307-4def-9b53-bda11a1177d5/download/",
"https://dandiarchive.s3.amazonaws.com/blobs/498/891/4988917d-8182-4bd8-9e38-dd38c94c08fa"
],
"dateModified":
"2023-05-19T16:31:05.695885-04:00",
"datePublished":
"2023-05-19T20:43:22.840526+00:00",
"digest":
{
"dandi:dandi-etag":
"36a3a0bf7f9c5580f996993b0e09fcca-28",
"dandi:sha2-256":
"a626b7a3f8f1069ab324adc9ef8b8c835b50ad6dfb37200efd7b63b8d3480e88"
},
"encodingFormat":
"application/x-nwb",
"id":
"dandiasset:05acd77d-8307-4def-9b53-bda11a1177d5",
"identifier":
"05acd77d-8307-4def-9b53-bda11a1177d5",
"measurementTechnique":
[],
"path":
"sub-Fig4-5-Bi100us-13/sub-Fig4-5-Bi100us-13_ses-BPAE-5xBipolar-100us_image.nwb",
"publishedBy":
{
"endDate":
"2023-05-19T20:43:22.840526+00:00",
"id":
"urn:uuid:9bcfe463-c1e3-474f-8eea-0d8c51059f84",
"name":
"DANDI publish",
"schemaKey":
"PublishActivity",
"startDate":
"2023-05-19T20:43:22.840526+00:00",
"wasAssociatedWith":
[
{
"id":
"urn:uuid:c37f4e20-a30c-4544-9d8e-f2b7f3cc8822",
"identifier":
"RRID:SCR_017571",
"name":
"DANDI API",
"schemaKey":
"Software",
"version":
"0.1.0"
}
]
},
"schemaKey":
"Asset",
"schemaVersion":
"0.6.4",
"variableMeasured":
[],
"wasAttributedTo":
[
{
"age":
{
"schemaKey":
"PropertyValue",
"unitText":
"ISO-8601 duration",
"value":
"P1D",
"valueReference":
{
"schemaKey":
"PropertyValue",
"value":
"dandi:BirthReference"
}
},
"identifier":
"Fig4_5_Bi100us_13",
"schemaKey":
"Participant",
"sex":
{
"name":
"Unknown",
"schemaKey":
"SexType"
},
"species":
{
"identifier":
"http://purl.obolibrary.org/obo/NCBITaxon_9913",
"name":
"Bos taurus - Cattle",
"schemaKey":
"SpeciesType"
}
}
],
"wasGeneratedBy":
[
{
"description":
"Cells were electroporated by a train of 5 100+100 us bipolar pulses (amplitude of the second phase was 50% the first phase's amplitude) at 1 Hz.The electrodes were two parallel stainless-steel cylinders, 1.5 mm in diameter and 3 mm apart",
"identifier":
"BPAE_5xBipolar_100us",
"name":
"BPAE_5xBipolar_100us",
"schemaKey":
"Session",
"startDate":
"2021-11-20T23:07:29-05:00"
},
{
"description":
"Metadata generated by DANDI cli",
"endDate":
"2023-05-19T16:31:05.694876-04:00",
"id":
"urn:uuid:3c52f81c-5bdc-439c-8473-3adad205dd6c",
"name":
"Metadata generation",
"schemaKey":
"Activity",
"startDate":
"2023-05-19T16:31:05.559709-04:00",
"wasAssociatedWith":
[
{
"identifier":
"RRID:SCR_019009",
"name":
"DANDI Command Line Interface",
"schemaKey":
"Software",
"url":
"https://github.com/dandi/dandi-cli",
"version":
"0.55.0"
}
]
}
]
},
"modified":
"2023-05-19T20:43:22.842071+00:00",
"path":
"sub-Fig4-5-Bi100us-13/sub-Fig4-5-Bi100us-13_ses-BPAE-5xBipolar-100us_image.nwb",
"size":
1871663171
},
{
"asset_id":
"94a5ecec-65ce-4aae-8e67-0c79b99def6a",
"blob":
"94213602-eacd-4a5e-8877-d0100e08f076",
"created":
"2023-05-19T20:32:08.944220+00:00",
"metadata":
{
"@context":
"https://raw.githubusercontent.com/dandi/schema/master/releases/0.6.4/context.json",
"access":
[
{
"schemaKey":
"AccessRequirements",
"status":
"dandi:OpenAccess"
}
],
"approach":
[],
"blobDateModified":
"2023-05-19T16:19:50.172619-04:00",
"contentSize":
1048668495,
"contentUrl":
[
"https://api.dandiarchive.org/api/assets/94a5ecec-65ce-4aae-8e67-0c79b99def6a/download/",
"https://dandiarchive.s3.amazonaws.com/blobs/942/136/94213602-eacd-4a5e-8877-d0100e08f076"
],
"dateModified":
"2023-05-19T16:30:58.203238-04:00",
"datePublished":
"2023-05-19T20:43:22.809402+00:00",
"digest":
{
"dandi:dandi-etag":
"1f59ff677959355f8f08f920cd99db60-16",
"dandi:sha2-256":
"287cd0e275bb5d7d1bddef9ce9423a672f95b68703ddc804a29a1d0ac5698d73"
},
"encodingFormat":
"application/x-nwb",
"id":
"dandiasset:94a5ecec-65ce-4aae-8e67-0c79b99def6a",
"identifier":
"94a5ecec-65ce-4aae-8e67-0c79b99def6a",
"measurementTechnique":
[],
"path":
"sub-Fig4-5-Bi1200ns-02/sub-Fig4-5-Bi1200ns-02_ses-BPAE-5xBipolar-1200ns_image.nwb",
"publishedBy":
{
"endDate":
"2023-05-19T20:43:22.809402+00:00",
"id":
"urn:uuid:895a5277-09f1-431d-a489-e8b707a04b49",
"name":
"DANDI publish",
"schemaKey":
"PublishActivity",
"startDate":
"2023-05-19T20:43:22.809402+00:00",
"wasAssociatedWith":
[
{
"id":
"urn:uuid:cec562ca-bc34-4da2-a36a-0e8f12365270",
"identifier":
"RRID:SCR_017571",
"name":
"DANDI API",
"schemaKey":
"Software",
"version":
"0.1.0"
}
]
},
"schemaKey":
"Asset",
"schemaVersion":
"0.6.4",
"variableMeasured":
[],
"wasAttributedTo":
[
{
"age":
{
"schemaKey":
"PropertyValue",
"unitText":
"ISO-8601 duration",
"value":
"P1D",
"valueReference":
{
"schemaKey":
"PropertyValue",
"value":
"dandi:BirthReference"
}
},
"identifier":
"Fig4_5_Bi1200ns_02",
"schemaKey":
"Participant",
"sex":
{
"name":
"Unknown",
"schemaKey":
"SexType"
},
"species":
{
"identifier":
"http://purl.obolibrary.org/obo/NCBITaxon_9913",
"name":
"Bos taurus - Cattle",
"schemaKey":
"SpeciesType"
}
}
],
"wasGeneratedBy":
[
{
"description":
"Cells were electroporated by a train of 5 1200+1200 ns bipolar pulses (amplitude of the second phase was 50% the first phase's amplitude) at 1 Hz.The electrodes were two parallel stainless-steel cylinders, 1.5 mm in diameter and 3 mm apart",
"identifier":
"BPAE_5xBipolar_1200ns",
"name":
"BPAE_5xBipolar_1200ns",
"schemaKey":
"Session",
"startDate":
"2021-09-01T17:09:20-04:00"
},
{
"description":
"Metadata generated by DANDI cli",
"endDate":
"2023-05-19T16:30:58.203238-04:00",
"id":
"urn:uuid:a5c807df-cca1-4f4e-9397-081f6493da9c",
"name":
"Metadata generation",
"schemaKey":
"Activity",
"startDate":
"2023-05-19T16:30:57.347026-04:00",
"wasAssociatedWith":
[
{
"identifier":
"RRID:SCR_019009",
"name":
"DANDI Command Line Interface",
"schemaKey":
"Software",
"url":
"https://github.com/dandi/dandi-cli",
"version":
"0.55.0"
}
]
}
]
},
"modified":
"2023-05-19T20:43:22.813283+00:00",
"path":
"sub-Fig4-5-Bi1200ns-02/sub-Fig4-5-Bi1200ns-02_ses-BPAE-5xBipolar-1200ns_image.nwb",
"size":
1048668495
},
{
"asset_id":
"4729dc01-618a-4cf2-88cd-86e2768716b9",
"blob":
"2379c9bd-ebea-4eff-bbd6-2ae3600eb193",
"created":
"2023-05-19T20:33:32.689574+00:00",
"metadata":
{
"@context":
"https://raw.githubusercontent.com/dandi/schema/master/releases/0.6.4/context.json",
"access":
[
{
"schemaKey":
"AccessRequirements",
"status":
"dandi:OpenAccess"
}
],
"approach":
[],
"blobDateModified":
"2023-05-19T16:23:12.227593-04:00",
"contentSize":
1882019718,
"contentUrl":
[
"https://api.dandiarchive.org/api/assets/4729dc01-618a-4cf2-88cd-86e2768716b9/download/",
"https://dandiarchive.s3.amazonaws.com/blobs/237/9c9/2379c9bd-ebea-4eff-bbd6-2ae3600eb193"
],
"dateModified":
"2023-05-19T16:31:05.168220-04:00",
"datePublished":
"2023-05-19T20:43:22.833150+00:00",
"digest":
{
"dandi:dandi-etag":
"ad27073a89d62039f0b55b8f1030a7d0-29",
"dandi:sha2-256":
"133f6e27e979e777eac142ca70f87a0851351c57f2d4220fa5a2b9c3252fe56b"
},
"encodingFormat":
"application/x-nwb",
"id":
"dandiasset:4729dc01-618a-4cf2-88cd-86e2768716b9",
"identifier":
"4729dc01-618a-4cf2-88cd-86e2768716b9",
"measurementTechnique":
[],
"path":
"sub-Fig4-5-Bi1200ns-03/sub-Fig4-5-Bi1200ns-03_ses-BPAE-5xBipolar-1200ns_image.nwb",
"publishedBy":
{
"endDate":
"2023-05-19T20:43:22.833150+00:00",
"id":
"urn:uuid:f49b1692-feeb-4962-b834-c1c7f0b26d81",
"name":
"DANDI publish",
"schemaKey":
"PublishActivity",
"startDate":
"2023-05-19T20:43:22.833150+00:00",
"wasAssociatedWith":
[
{
"id":
"urn:uuid:165d8321-3331-4d20-a910-cde095e72737",
"identifier":
"RRID:SCR_017571",
"name":
"DANDI API",
"schemaKey":
"Software",
"version":
"0.1.0"
}
]
},
"schemaKey":
"Asset",
"schemaVersion":
"0.6.4",
"variableMeasured":
[],
"wasAttributedTo":
[
{
"age":
{
"schemaKey":
"PropertyValue",
"unitText":
"ISO-8601 duration",
"value":
"P1D",
"valueReference":
{
"schemaKey":
"PropertyValue",
"value":
"dandi:BirthReference"
}
},
"identifier":
"Fig4_5_Bi1200ns_03",
"schemaKey":
"Participant",
"sex":
{
"name":
"Unknown",
"schemaKey":
"SexType"
},
"species":
{
"identifier":
"http://purl.obolibrary.org/obo/NCBITaxon_9913",
"name":
"Bos taurus - Cattle",
"schemaKey":
"SpeciesType"
}
}
],
"wasGeneratedBy":
[
{
"description":
"Cells were electroporated by a train of 5 1200+1200 ns bipolar pulses (amplitude of the second phase was 50% the first phase's amplitude) at 1 Hz.The electrodes were two parallel stainless-steel cylinders, 1.5 mm in diameter and 3 mm apart",
"identifier":
"BPAE_5xBipolar_1200ns",
"name":
"BPAE_5xBipolar_1200ns",
"schemaKey":
"Session",
"startDate":
"2021-10-11T12:48:50-04:00"
},
{
"description":
"Metadata generated by DANDI cli",
"endDate":
"2023-05-19T16:31:05.168220-04:00",
"id":
"urn:uuid:6e47d4ba-6346-4236-8774-c3a905f2186c",
"name":
"Metadata generation",
"schemaKey":
"Activity",
"startDate":
"2023-05-19T16:31:05.086859-04:00",
"wasAssociatedWith":
[
{
"identifier":
"RRID:SCR_019009",
"name":
"DANDI Command Line Interface",
"schemaKey":
"Software",
"url":
"https://github.com/dandi/dandi-cli",
"version":
"0.55.0"
}
]
}
]
},
"modified":
"2023-05-19T20:43:22.834508+00:00",
"path":
"sub-Fig4-5-Bi1200ns-03/sub-Fig4-5-Bi1200ns-03_ses-BPAE-5xBipolar-1200ns_image.nwb",
"size":
1882019718
},
{
"asset_id":
"cdfa6bd6-bef8-4d24-b847-4c05a10f0b5e",
"blob":
"62ab5424-09c7-4463-8969-b4f5d2abd8bd",
"created":
"2023-05-19T20:33:36.063332+00:00",
"metadata":
{
"@context":
"https://raw.githubusercontent.com/dandi/schema/master/releases/0.6.4/context.json",
"access":
[
{
"schemaKey":
"AccessRequirements",
"status":
"dandi:OpenAccess"
}
],
"approach":
[],
"blobDateModified":
"2023-05-19T16:25:44.504405-04:00",
"contentSize":
1046806626,
"contentUrl":
[
"https://api.dandiarchive.org/api/assets/cdfa6bd6-bef8-4d24-b847-4c05a10f0b5e/download/",
"https://dandiarchive.s3.amazonaws.com/blobs/62a/b54/62ab5424-09c7-4463-8969-b4f5d2abd8bd"
],
"dateModified":
"2023-05-19T16:32:14.498999-04:00",
"datePublished":
"2023-05-19T20:43:22.921239+00:00",
"digest":
{
"dandi:dandi-etag":
"1722e0f348ac5bcb1490e9bea0e7df92-16",
"dandi:sha2-256":
"19bbf185824e2c02ca417bacdee0d6ef95de09715a8bba50ef15a3a539219cd3"
},
"encodingFormat":
"application/x-nwb",
"id":
"dandiasset:cdfa6bd6-bef8-4d24-b847-4c05a10f0b5e",
"identifier":
"cdfa6bd6-bef8-4d24-b847-4c05a10f0b5e",
"measurementTechnique":
[],
"path":
"sub-Fig4-5-Bi1200ns-14/sub-Fig4-5-Bi1200ns-14_ses-BPAE-5xBipolar-1200ns_image.nwb",
"publishedBy":
{
"endDate":
"2023-05-19T20:43:22.921239+00:00",
"id":
"urn:uuid:cc9188b5-ecce-4a60-b41f-0f54e45b9edc",
"name":
"DANDI publish",
"schemaKey":
"PublishActivity",
"startDate":
"2023-05-19T20:43:22.921239+00:00",
"wasAssociatedWith":
[
{
"id":
"urn:uuid:395af148-98da-421a-96ff-fbb5dbc01b3b",
"identifier":
"RRID:SCR_017571",
"name":
"DANDI API",
"schemaKey":
"Software",
"version":
"0.1.0"
}
]
},
"schemaKey":
"Asset",
"schemaVersion":
"0.6.4",
"variableMeasured":
[],
"wasAttributedTo":
[
{
"age":
{
"schemaKey":
"PropertyValue",
"unitText":
"ISO-8601 duration",
"value":
"P1D",
"valueReference":
{
"schemaKey":
"PropertyValue",
"value":
"dandi:BirthReference"
}
},
"identifier":
"Fig4_5_Bi1200ns_14",
"schemaKey":
"Participant",
"sex":
{
"name":
"Unknown",
"schemaKey":
"SexType"
},
"species":
{
"identifier":
"http://purl.obolibrary.org/obo/NCBITaxon_9913",
"name":
"Bos taurus - Cattle",
"schemaKey":
"SpeciesType"
}
}
],
"wasGeneratedBy":
[
{
"description":
"Cells were electroporated by a train of 5 1200+1200 ns bipolar pulses (amplitude of the second phase was 50% the first phase's amplitude) at 1 Hz.The electrodes were two parallel stainless-steel cylinders, 1.5 mm in diameter and 3 mm apart",
"identifier":
"BPAE_5xBipolar_1200ns",
"name":
"BPAE_5xBipolar_1200ns",
"schemaKey":
"Session",
"startDate":
"2021-09-01T20:28:04-04:00"
},
{
"description":
"Metadata generated by DANDI cli",
"endDate":
"2023-05-19T16:32:14.498999-04:00",
"id":
"urn:uuid:7572f22f-027b-4eee-84fb-b4e70fbcc7bb",
"name":
"Metadata generation",
"schemaKey":
"Activity",
"startDate":
"2023-05-19T16:32:14.443821-04:00",
"wasAssociatedWith":
[
{
"identifier":
"RRID:SCR_019009",
"name":
"DANDI Command Line Interface",
"schemaKey":
"Software",
"url":
"https://github.com/dandi/dandi-cli",
"version":
"0.55.0"
}
]
}
]
},
"modified":
"2023-05-19T20:43:22.922978+00:00",
"path":
"sub-Fig4-5-Bi1200ns-14/sub-Fig4-5-Bi1200ns-14_ses-BPAE-5xBipolar-1200ns_image.nwb",
"size":
1046806626
},
{
"asset_id":
"ecd4cc5c-41bb-4c07-b20f-9b3036da1109",
"blob":
"8bc7d0c4-8eba-4234-87ee-54e7bba54e02",
"created":
"2023-05-19T20:34:11.844515+00:00",
"metadata":
{
"@context":
"https://raw.githubusercontent.com/dandi/schema/master/releases/0.6.4/context.json",
"access":
[
{
"schemaKey":
"AccessRequirements",
"status":
"dandi:OpenAccess"
}
],
"approach":
[],
"blobDateModified":
"2023-05-19T15:58:00.731691-04:00",
"contentSize":
1010856797,
"contentUrl":
[
"https://api.dandiarchive.org/api/assets/ecd4cc5c-41bb-4c07-b20f-9b3036da1109/download/",
"https://dandiarchive.s3.amazonaws.com/blobs/8bc/7d0/8bc7d0c4-8eba-4234-87ee-54e7bba54e02"
],
"dateModified":
"2023-05-19T16:33:23.367354-04:00",
"datePublished":
"2023-05-19T20:43:22.928196+00:00",
"digest":
{
"dandi:dandi-etag":
"b822f5b42107c812851a43827ab2c3e3-16",
"dandi:sha2-256":
"63605a12a6d1661df611b7931df3bf68ce7da4298675eb16f31677f00d08f72b"
},
"encodingFormat":
"application/x-nwb",
"id":
"dandiasset:ecd4cc5c-41bb-4c07-b20f-9b3036da1109",
"identifier":
"ecd4cc5c-41bb-4c07-b20f-9b3036da1109",
"measurementTechnique":
[],
"path":
"sub-Fig4-5-Bi300ns-04/sub-Fig4-5-Bi300ns-04_ses-BPAE-5xBipolar-300ns_image.nwb",
"publishedBy":
{
"endDate":
"2023-05-19T20:43:22.928196+00:00",
"id":
"urn:uuid:8b877d1c-0f71-44d5-8b24-c04dcb817dec",
"name":
"DANDI publish",
"schemaKey":
"PublishActivity",
"startDate":
"2023-05-19T20:43:22.928196+00:00",
"wasAssociatedWith":
[
{
"id":
"urn:uuid:aee5cd59-a3cc-4116-9a56-5b8dd180c19b",
"identifier":
"RRID:SCR_017571",
"name":
"DANDI API",
"schemaKey":
"Software",
"version":
"0.1.0"
}
]
},
"schemaKey":
"Asset",
"schemaVersion":
"0.6.4",
"variableMeasured":
[],
"wasAttributedTo":
[
{
"age":
{
"schemaKey":
"PropertyValue",
"unitText":
"ISO-8601 duration",
"value":
"P1D",
"valueReference":
{
"schemaKey":
"PropertyValue",
"value":
"dandi:BirthReference"
}
},
"identifier":
"Fig4_5_Bi300ns_04",
"schemaKey":
"Participant",
"sex":
{
"name":
"Unknown",
"schemaKey":
"SexType"
},
"species":
{
"identifier":
"http://purl.obolibrary.org/obo/NCBITaxon_9913",
"name":
"Bos taurus - Cattle",
"schemaKey":
"SpeciesType"
}
}
],
"wasGeneratedBy":
[
{
"description":
"Cells were electroporated by a train of 5 300+300 ns bipolar pulses (amplitude of the second phase was 50% the first phase's amplitude) at 1 Hz.The electrodes were two parallel stainless-steel cylinders, 1.5 mm in diameter and 3 mm apart",
"identifier":
"BPAE_5xBipolar_300ns",
"name":
"BPAE_5xBipolar_300ns",
"schemaKey":
"Session",
"startDate":
"2021-08-14T15:16:58-04:00"
},
{
"description":
"Metadata generated by DANDI cli",
"endDate":
"2023-05-19T16:33:23.367354-04:00",
"id":
"urn:uuid:528b7974-5211-4634-a3ff-d2c8edb38990",
"name":
"Metadata generation",
"schemaKey":
"Activity",
"startDate":
"2023-05-19T16:33:23.316530-04:00",
"wasAssociatedWith":
[
{
"identifier":
"RRID:SCR_019009",
"name":
"DANDI Command Line Interface",
"schemaKey":
"Software",
"url":
"https://github.com/dandi/dandi-cli",
"version":
"0.55.0"
}
]
}
]
},
"modified":
"2023-05-19T20:43:22.929794+00:00",
"path":
"sub-Fig4-5-Bi300ns-04/sub-Fig4-5-Bi300ns-04_ses-BPAE-5xBipolar-300ns_image.nwb",
"size":
1010856797
},
{
"asset_id":
"948fe67d-2b46-4902-8f06-21a24f6c0fc2",
"blob":
"e03556b3-9c26-4e9a-bd40-6483d260bb3c",
"created":
"2023-05-19T20:34:49.820016+00:00",
"metadata":
{
"@context":
"https://raw.githubusercontent.com/dandi/schema/master/releases/0.6.4/context.json",
"access":
[
{
"schemaKey":
"AccessRequirements",
"status":
"dandi:OpenAccess"
}
],
"approach":
[],
"blobDateModified":
"2023-05-19T15:59:42.801303-04:00",
"contentSize":
1013643377,
"contentUrl":
[
"https://api.dandiarchive.org/api/assets/948fe67d-2b46-4902-8f06-21a24f6c0fc2/download/",
"https://dandiarchive.s3.amazonaws.com/blobs/e03/556/e03556b3-9c26-4e9a-bd40-6483d260bb3c"
],
"dateModified":
"2023-05-19T16:33:37.380568-04:00",
"datePublished":
"2023-05-19T20:43:22.849120+00:00",
"digest":
{
"dandi:dandi-etag":
"4356b625899b1cfb3102648f9a5aa733-16",
"dandi:sha2-256":
"ce6b3f750755ca0c405ce7a58e65f77321105a07d70d90da526cd167731fd174"
},
"encodingFormat":
"application/x-nwb",
"id":
"dandiasset:948fe67d-2b46-4902-8f06-21a24f6c0fc2",
"identifier":
"948fe67d-2b46-4902-8f06-21a24f6c0fc2",
"measurementTechnique":
[],
"path":
"sub-Fig4-5-Bi300ns-08/sub-Fig4-5-Bi300ns-08_ses-BPAE-5xBipolar-300ns_image.nwb",
"publishedBy":
{
"endDate":
"2023-05-19T20:43:22.849120+00:00",
"id":
"urn:uuid:48203419-c933-4aae-8cb5-d809e91ee501",
"name":
"DANDI publish",
"schemaKey":
"PublishActivity",
"startDate":
"2023-05-19T20:43:22.849120+00:00",
"wasAssociatedWith":
[
{
"id":
"urn:uuid:ba564701-8f3e-4063-98a3-6bc5ae082c2f",
"identifier":
"RRID:SCR_017571",
"name":
"DANDI API",
"schemaKey":
"Software",
"version":
"0.1.0"
}
]
},
"schemaKey":
"Asset",
"schemaVersion":
"0.6.4",
"variableMeasured":
[],
"wasAttributedTo":
[
{
"age":
{
"schemaKey":
"PropertyValue",
"unitText":
"ISO-8601 duration",
"value":
"P1D",
"valueReference":
{
"schemaKey":
"PropertyValue",
"value":
"dandi:BirthReference"
}
},
"identifier":
"Fig4_5_Bi300ns_08",
"schemaKey":
"Participant",
"sex":
{
"name":
"Unknown",
"schemaKey":
"SexType"
},
"species":
{
"identifier":
"http://purl.obolibrary.org/obo/NCBITaxon_9913",
"name":
"Bos taurus - Cattle",
"schemaKey":
"SpeciesType"
}
}
],
"wasGeneratedBy":
[
{
"description":
"Cells were electroporated by a train of 5 300+300 ns bipolar pulses (amplitude of the second phase was 50% the first phase's amplitude) at 1 Hz.The electrodes were two parallel stainless-steel cylinders, 1.5 mm in diameter and 3 mm apart",
"identifier":
"BPAE_5xBipolar_300ns",
"name":
"BPAE_5xBipolar_300ns",
"schemaKey":
"Session",
"startDate":
"2021-08-14T16:15:28-04:00"
},
{
"description":
"Metadata generated by DANDI cli",
"endDate":
"2023-05-19T16:33:37.380568-04:00",
"id":
"urn:uuid:54346ada-0c1f-4736-b148-659705a8f003",
"name":
"Metadata generation",
"schemaKey":
"Activity",
"startDate":
"2023-05-19T16:33:36.887177-04:00",
"wasAssociatedWith":
[
{
"identifier":
"RRID:SCR_019009",
"name":
"DANDI Command Line Interface",
"schemaKey":
"Software",
"url":
"https://github.com/dandi/dandi-cli",
"version":
"0.55.0"
}
]
}
]
},
"modified":
"2023-05-19T20:43:22.850756+00:00",
"path":
"sub-Fig4-5-Bi300ns-08/sub-Fig4-5-Bi300ns-08_ses-BPAE-5xBipolar-300ns_image.nwb",
"size":
1013643377
},
{
"asset_id":
"68f0f7d7-72bd-46cc-8834-9da69c4ba377",
"blob":
"21cef986-0ab8-468d-ac25-e1aae24c389d",
"created":
"2023-05-19T20:34:53.663575+00:00",
"metadata":
{
"@context":
"https://raw.githubusercontent.com/dandi/schema/master/releases/0.6.4/context.json",
"access":
[
{
"schemaKey":
"AccessRequirements",
"status":
"dandi:OpenAccess"
}
],
"approach":
[],
"blobDateModified":
"2023-05-19T16:03:58.235517-04:00",
"contentSize":
1017896937,
"contentUrl":
[
"https://api.dandiarchive.org/api/assets/68f0f7d7-72bd-46cc-8834-9da69c4ba377/download/",
"https://dandiarchive.s3.amazonaws.com/blobs/21c/ef9/21cef986-0ab8-468d-ac25-e1aae24c389d"
],
"dateModified":
"2023-05-19T16:33:41.022760-04:00",
"datePublished":
"2023-05-19T20:43:22.935086+00:00",
"digest":
{
"dandi:dandi-etag":
"905393d50c9d06537c0ef61f36e27b36-16",
"dandi:sha2-256":
"7bdf15b9cae98de20e09b21ab94a53b21343359a8a2a664af84217176179ef25"
},
"encodingFormat":
"application/x-nwb",
"id":
"dandiasset:68f0f7d7-72bd-46cc-8834-9da69c4ba377",
"identifier":
"68f0f7d7-72bd-46cc-8834-9da69c4ba377",
"measurementTechnique":
[],
"path":
"sub-Fig4-5-Bi300ns-15/sub-Fig4-5-Bi300ns-15_ses-BPAE-5xBipolar-300ns_image.nwb",
"publishedBy":
{
"endDate":
"2023-05-19T20:43:22.935086+00:00",
"id":
"urn:uuid:ae25420a-afa2-4b99-9002-c69229bac37c",
"name":
"DANDI publish",
"schemaKey":
"PublishActivity",
"startDate":
"2023-05-19T20:43:22.935086+00:00",
"wasAssociatedWith":
[
{
"id":
"urn:uuid:59479ebf-4cba-4040-bcbd-686b3aec8ebc",
"identifier":
"RRID:SCR_017571",
"name":
"DANDI API",
"schemaKey":
"Software",
"version":
"0.1.0"
}
]
},
"schemaKey":
"Asset",
"schemaVersion":
"0.6.4",
"variableMeasured":
[],
"wasAttributedTo":
[
{
"age":
{
"schemaKey":
"PropertyValue",
"unitText":
"ISO-8601 duration",
"value":
"P1D",
"valueReference":
{
"schemaKey":
"PropertyValue",
"value":
"dandi:BirthReference"
}
},
"identifier":
"Fig4_5_Bi300ns_15",
"schemaKey":
"Participant",
"sex":
{
"name":
"Unknown",
"schemaKey":
"SexType"
},
"species":
{
"identifier":
"http://purl.obolibrary.org/obo/NCBITaxon_9913",
"name":
"Bos taurus - Cattle",
"schemaKey":
"SpeciesType"
}
}
],
"wasGeneratedBy":
[
{
"description":
"Cells were electroporated by a train of 5 300+300 ns bipolar pulses (amplitude of the second phase was 50% the first phase's amplitude) at 1 Hz.The electrodes were two parallel stainless-steel cylinders, 1.5 mm in diameter and 3 mm apart",
"identifier":
"BPAE_5xBipolar_300ns",
"name":
"BPAE_5xBipolar_300ns",
"schemaKey":
"Session",
"startDate":
"2021-08-14T17:59:27-04:00"
},
{
"description":
"Metadata generated by DANDI cli",
"endDate":
"2023-05-19T16:33:41.022760-04:00",
"id":
"urn:uuid:0bfd756a-c4b0-4ed1-8030-240697e4b3e6",
"name":
"Metadata generation",
"schemaKey":
"Activity",
"startDate":
"2023-05-19T16:33:40.962374-04:00",
"wasAssociatedWith":
[
{
"identifier":
"RRID:SCR_019009",
"name":
"DANDI Command Line Interface",
"schemaKey":
"Software",
"url":
"https://github.com/dandi/dandi-cli",
"version":
"0.55.0"
}
]
}
]
},
"modified":
"2023-05-19T20:43:22.936526+00:00",
"path":
"sub-Fig4-5-Bi300ns-15/sub-Fig4-5-Bi300ns-15_ses-BPAE-5xBipolar-300ns_image.nwb",
"size":
1017896937
},
{
"asset_id":
"e8d4f1c9-21cf-4891-9834-9917671b5668",
"blob":
"6e2fd133-4aed-4f57-9ead-7da52ed7aaef",
"created":
"2023-05-19T20:36:06.463217+00:00",
"metadata":
{
"@context":
"https://raw.githubusercontent.com/dandi/schema/master/releases/0.6.4/context.json",
"access":
[
{
"schemaKey":
"AccessRequirements",
"status":
"dandi:OpenAccess"
}
],
"approach":
[],
"blobDateModified":
"2023-05-19T16:10:02.031792-04:00",
"contentSize":
1894627769,
"contentUrl":
[
"https://api.dandiarchive.org/api/assets/e8d4f1c9-21cf-4891-9834-9917671b5668/download/",
"https://dandiarchive.s3.amazonaws.com/blobs/6e2/fd1/6e2fd133-4aed-4f57-9ead-7da52ed7aaef"
],
"dateModified":
"2023-05-19T16:33:45.152692-04:00",
"datePublished":
"2023-05-19T20:43:22.942417+00:00",
"digest":
{
"dandi:dandi-etag":
"1076ec765fe40427c92f09eb3ab8e2bc-29",
"dandi:sha2-256":
"f08e416ed14be8613fab08c874d2b992161da381529cb72b61fabff5e6c0cfba"
},
"encodingFormat":
"application/x-nwb",
"id":
"dandiasset:e8d4f1c9-21cf-4891-9834-9917671b5668",
"identifier":
"e8d4f1c9-21cf-4891-9834-9917671b5668",
"measurementTechnique":
[],
"path":
"sub-Fig4-5-Bi500us-08/sub-Fig4-5-Bi500us-08_ses-BPAE-5xBipolar-500us_image.nwb",
"publishedBy":
{
"endDate":
"2023-05-19T20:43:22.942417+00:00",
"id":
"urn:uuid:ef990644-d061-4310-81fc-39e7ec622590",
"name":
"DANDI publish",
"schemaKey":
"PublishActivity",
"startDate":
"2023-05-19T20:43:22.942417+00:00",
"wasAssociatedWith":
[
{
"id":
"urn:uuid:8fb5c159-cce0-4700-8784-e7165c9cd868",
"identifier":
"RRID:SCR_017571",
"name":
"DANDI API",
"schemaKey":
"Software",
"version":
"0.1.0"
}
]
},
"schemaKey":
"Asset",
"schemaVersion":
"0.6.4",
"variableMeasured":
[],
"wasAttributedTo":
[
{
"age":
{
"schemaKey":
"PropertyValue",
"unitText":
"ISO-8601 duration",
"value":
"P1D",
"valueReference":
{
"schemaKey":
"PropertyValue",
"value":
"dandi:BirthReference"
}
},
"identifier":
"Fig4_5_Bi500us_08",
"schemaKey":
"Participant",
"sex":
{
"name":
"Unknown",
"schemaKey":
"SexType"
},
"species":
{
"identifier":
"http://purl.obolibrary.org/obo/NCBITaxon_9913",
"name":
"Bos taurus - Cattle",
"schemaKey":
"SpeciesType"
}
}
],
"wasGeneratedBy":
[
{
"description":
"Cells were electroporated by a train of 5 500+500 us bipolar pulses (amplitude of the second phase was 50% the first phase's amplitude) at 1 Hz.The electrodes were two parallel stainless-steel cylinders, 1.5 mm in diameter and 3 mm apart",
"identifier":
"BPAE_5xBipolar_500us",
"name":
"BPAE_5xBipolar_500us",
"schemaKey":
"Session",
"startDate":
"2021-12-04T18:39:16-05:00"
},
{
"description":
"Metadata generated by DANDI cli",
"endDate":
"2023-05-19T16:33:45.152692-04:00",
"id":
"urn:uuid:bb802c3d-2756-47c4-b3dc-3ec6b80af638",
"name":
"Metadata generation",
"schemaKey":
"Activity",
"startDate":
"2023-05-19T16:33:45.057129-04:00",
"wasAssociatedWith":
[
{
"identifier":
"RRID:SCR_019009",
"name":
"DANDI Command Line Interface",
"schemaKey":
"Software",
"url":
"https://github.com/dandi/dandi-cli",
"version":
"0.55.0"
}
]
}
]
},
"modified":
"2023-05-19T20:43:22.943925+00:00",
"path":
"sub-Fig4-5-Bi500us-08/sub-Fig4-5-Bi500us-08_ses-BPAE-5xBipolar-500us_image.nwb",
"size":
1894627769
},
{
"asset_id":
"2a7b2dc1-364b-45c2-96fb-9b1c73e5edd4",
"blob":
"40c18492-8298-4953-8491-876ecf8ea52a",
"created":
"2023-05-19T20:36:11.584087+00:00",
"metadata":
{
"@context":
"https://raw.githubusercontent.com/dandi/schema/master/releases/0.6.4/context.json",
"access":
[
{
"schemaKey":
"AccessRequirements",
"status":
"dandi:OpenAccess"
}
],
"approach":
[],
"blobDateModified":
"2023-05-19T16:12:54.650018-04:00",
"contentSize":
1885049880,
"contentUrl":
[
"https://api.dandiarchive.org/api/assets/2a7b2dc1-364b-45c2-96fb-9b1c73e5edd4/download/",
"https://dandiarchive.s3.amazonaws.com/blobs/40c/184/40c18492-8298-4953-8491-876ecf8ea52a"
],
"dateModified":
"2023-05-19T16:33:47.250792-04:00",
"datePublished":
"2023-05-19T20:43:22.954666+00:00",
"digest":
{
"dandi:dandi-etag":
"c1ee33e857a8ba968a446f91e15c04b4-29",
"dandi:sha2-256":
"d2e83d475449ac1a7349815e3e8bfa2657d3a94fb830371c69c56d6469bd9d74"
},
"encodingFormat":
"application/x-nwb",
"id":
"dandiasset:2a7b2dc1-364b-45c2-96fb-9b1c73e5edd4",
"identifier":
"2a7b2dc1-364b-45c2-96fb-9b1c73e5edd4",
"measurementTechnique":
[],
"path":
"sub-Fig4-5-Bi500us-10/sub-Fig4-5-Bi500us-10_ses-BPAE-5xBipolar-500us_image.nwb",
"publishedBy":
{
"endDate":
"2023-05-19T20:43:22.954666+00:00",
"id":
"urn:uuid:3fb356d7-9929-4221-95bd-ba4186357f35",
"name":
"DANDI publish",
"schemaKey":
"PublishActivity",
"startDate":
"2023-05-19T20:43:22.954666+00:00",
"wasAssociatedWith":
[
{
"id":
"urn:uuid:036f23ca-64f3-40aa-8003-be4fb720b394",
"identifier":
"RRID:SCR_017571",
"name":
"DANDI API",
"schemaKey":
"Software",
"version":
"0.1.0"
}
]
},
"schemaKey":
"Asset",
"schemaVersion":
"0.6.4",
"variableMeasured":
[],
"wasAttributedTo":
[
{
"age":
{
"schemaKey":
"PropertyValue",
"unitText":
"ISO-8601 duration",
"value":
"P1D",
"valueReference":
{
"schemaKey":
"PropertyValue",
"value":
"dandi:BirthReference"
}
},
"identifier":
"Fig4_5_Bi500us_10",
"schemaKey":
"Participant",
"sex":
{
"name":
"Unknown",
"schemaKey":
"SexType"
},
"species":
{
"identifier":
"http://purl.obolibrary.org/obo/NCBITaxon_9913",
"name":
"Bos taurus - Cattle",
"schemaKey":
"SpeciesType"
}
}
],
"wasGeneratedBy":
[
{
"description":
"Cells were electroporated by a train of 5 500+500 us bipolar pulses (amplitude of the second phase was 50% the first phase's amplitude) at 1 Hz.The electrodes were two parallel stainless-steel cylinders, 1.5 mm in diameter and 3 mm apart",
"identifier":
"BPAE_5xBipolar_500us",
"name":
"BPAE_5xBipolar_500us",
"schemaKey":
"Session",
"startDate":
"2021-12-04T19:18:45-05:00"
},
{
"description":
"Metadata generated by DANDI cli",
"endDate":
"2023-05-19T16:33:47.250792-04:00",
"id":
"urn:uuid:1c04ea36-93a8-4107-92ce-d3d39a865f8d",
"name":
"Metadata generation",
"schemaKey":
"Activity",
"startDate":
"2023-05-19T16:33:47.197063-04:00",
"wasAssociatedWith":
[
{
"identifier":
"RRID:SCR_019009",
"name":
"DANDI Command Line Interface",
"schemaKey":
"Software",
"url":
"https://github.com/dandi/dandi-cli",
"version":
"0.55.0"
}
]
}
]
},
"modified":
"2023-05-19T20:43:22.956126+00:00",
"path":
"sub-Fig4-5-Bi500us-10/sub-Fig4-5-Bi500us-10_ses-BPAE-5xBipolar-500us_image.nwb",
"size":
1885049880
},
{
"asset_id":
"c86f8627-8dc9-45f1-8d2c-3199f01a04b4",
"blob":
"ac694213-817c-48c9-be96-0ed0a44947c6",
"created":
"2023-05-19T20:36:34.855758+00:00",
"metadata":
{
"@context":
"https://raw.githubusercontent.com/dandi/schema/master/releases/0.6.4/context.json",
"access":
[
{
"schemaKey":
"AccessRequirements",
"status":
"dandi:OpenAccess"
}
],
"approach":
[],
"blobDateModified":
"2023-05-19T15:31:37.313498-04:00",
"contentSize":
1876425314,
"contentUrl":
[
"https://api.dandiarchive.org/api/assets/c86f8627-8dc9-45f1-8d2c-3199f01a04b4/download/",
"https://dandiarchive.s3.amazonaws.com/blobs/ac6/942/ac694213-817c-48c9-be96-0ed0a44947c6"
],
"dateModified":
"2023-05-19T16:34:20.207226-04:00",
"datePublished":
"2023-05-19T20:43:22.973055+00:00",
"digest":
{
"dandi:dandi-etag":
"41d557ab6f4bcb3011da3a501e60dcf6-28",
"dandi:sha2-256":
"aeafc406d511e909a4382d3e305cab796ebe708af0f7301de77989fdd88d4d80"
},
"encodingFormat":
"application/x-nwb",
"id":
"dandiasset:c86f8627-8dc9-45f1-8d2c-3199f01a04b4",
"identifier":
"c86f8627-8dc9-45f1-8d2c-3199f01a04b4",
"measurementTechnique":
[],
"path":
"sub-Fig4-5-Bi50us-06/sub-Fig4-5-Bi50us-06_ses-BPAE-5xBipolar-50us_image.nwb",
"publishedBy":
{
"endDate":
"2023-05-19T20:43:22.973055+00:00",
"id":
"urn:uuid:bfcd1c4e-e606-4ff1-9211-ebd3ed3e7c78",
"name":
"DANDI publish",
"schemaKey":
"PublishActivity",
"startDate":
"2023-05-19T20:43:22.973055+00:00",
"wasAssociatedWith":
[
{
"id":
"urn:uuid:9b697511-4d37-4901-8924-897f03d6c047",
"identifier":
"RRID:SCR_017571",
"name":
"DANDI API",
"schemaKey":
"Software",
"version":
"0.1.0"
}
]
},
"schemaKey":
"Asset",
"schemaVersion":
"0.6.4",
"variableMeasured":
[],
"wasAttributedTo":
[
{
"age":
{
"schemaKey":
"PropertyValue",
"unitText":
"ISO-8601 duration",
"value":
"P1D",
"valueReference":
{
"schemaKey":
"PropertyValue",
"value":
"dandi:BirthReference"
}
},
"identifier":
"Fig4_5_Bi50us_06",
"schemaKey":
"Participant",
"sex":
{
"name":
"Unknown",
"schemaKey":
"SexType"
},
"species":
{
"identifier":
"http://purl.obolibrary.org/obo/NCBITaxon_9913",
"name":
"Bos taurus - Cattle",
"schemaKey":
"SpeciesType"
}
}
],
"wasGeneratedBy":
[
{
"description":
"Cells were electroporated by a train of 5 50+50 us bipolar pulses (amplitude of the second phase was 50% the first phase's amplitude) at 1 Hz.The electrodes were two parallel stainless-steel cylinders, 1.5 mm in diameter and 3 mm apart",
"identifier":
"BPAE_5xBipolar_50us",
"name":
"BPAE_5xBipolar_50us",
"schemaKey":
"Session",
"startDate":
"2021-11-06T16:42:19-04:00"
},
{
"description":
"Metadata generated by DANDI cli",
"endDate":
"2023-05-19T16:34:20.207226-04:00",
"id":
"urn:uuid:3db31a73-a15d-4098-901f-c9c0b7f26354",
"name":
"Metadata generation",
"schemaKey":
"Activity",
"startDate":
"2023-05-19T16:34:20.154769-04:00",
"wasAssociatedWith":
[
{
"identifier":
"RRID:SCR_019009",
"name":
"DANDI Command Line Interface",
"schemaKey":
"Software",
"url":
"https://github.com/dandi/dandi-cli",
"version":
"0.55.0"
}
]
}
]
},
"modified":
"2023-05-19T20:43:22.974894+00:00",
"path":
"sub-Fig4-5-Bi50us-06/sub-Fig4-5-Bi50us-06_ses-BPAE-5xBipolar-50us_image.nwb",
"size":
1876425314
},
{
"asset_id":
"1efa7bb3-ec63-4636-8284-0fd5d124e7bf",
"blob":
"1f9c84a8-ea77-4dd1-b278-1d451e47b1f5",
"created":
"2023-05-19T20:37:18.991299+00:00",
"metadata":
{
"@context":
"https://raw.githubusercontent.com/dandi/schema/master/releases/0.6.4/context.json",
"access":
[
{
"schemaKey":
"AccessRequirements",
"status":
"dandi:OpenAccess"
}
],
"approach":
[],
"blobDateModified":
"2023-05-19T15:35:42.714115-04:00",
"contentSize":
1868943367,
"contentUrl":
[
"https://api.dandiarchive.org/api/assets/1efa7bb3-ec63-4636-8284-0fd5d124e7bf/download/",
"https://dandiarchive.s3.amazonaws.com/blobs/1f9/c84/1f9c84a8-ea77-4dd1-b278-1d451e47b1f5"
],
"dateModified":
"2023-05-19T16:34:58.673396-04:00",
"datePublished":
"2023-05-19T20:43:22.983470+00:00",
"digest":
{
"dandi:dandi-etag":
"437e4d8971155bda5a801ea11f68ce2f-28",
"dandi:sha2-256":
"bb6ec53b4bd1eba9fe6a8fe7419cd6955fdc79afd3f81163e90580b09c78620f"
},
"encodingFormat":
"application/x-nwb",
"id":
"dandiasset:1efa7bb3-ec63-4636-8284-0fd5d124e7bf",
"identifier":
"1efa7bb3-ec63-4636-8284-0fd5d124e7bf",
"measurementTechnique":
[],
"path":
"sub-Fig4-5-Bi50us-08/sub-Fig4-5-Bi50us-08_ses-BPAE-5xBipolar-50us_image.nwb",
"publishedBy":
{
"endDate":
"2023-05-19T20:43:22.983470+00:00",
"id":
"urn:uuid:4c5e661f-61ad-4954-9fb0-09461a6ba6af",
"name":
"DANDI publish",
"schemaKey":
"PublishActivity",
"startDate":
"2023-05-19T20:43:22.983470+00:00",
"wasAssociatedWith":
[
{
"id":
"urn:uuid:a8cd1fb1-0c96-4bdb-a485-9c78f802c766",
"identifier":
"RRID:SCR_017571",
"name":
"DANDI API",
"schemaKey":
"Software",
"version":
"0.1.0"
}
]
},
"schemaKey":
"Asset",
"schemaVersion":
"0.6.4",
"variableMeasured":
[],
"wasAttributedTo":
[
{
"age":
{
"schemaKey":
"PropertyValue",
"unitText":
"ISO-8601 duration",
"value":
"P1D",
"valueReference":
{
"schemaKey":
"PropertyValue",
"value":
"dandi:BirthReference"
}
},
"identifier":
"Fig4_5_Bi50us_08",
"schemaKey":
"Participant",
"sex":
{
"name":
"Unknown",
"schemaKey":
"SexType"
},
"species":
{
"identifier":
"http://purl.obolibrary.org/obo/NCBITaxon_9913",
"name":
"Bos taurus - Cattle",
"schemaKey":
"SpeciesType"
}
}
],
"wasGeneratedBy":
[
{
"description":
"Cells were electroporated by a train of 5 50+50 us bipolar pulses (amplitude of the second phase was 50% the first phase's amplitude) at 1 Hz.The electrodes were two parallel stainless-steel cylinders, 1.5 mm in diameter and 3 mm apart",
"identifier":
"BPAE_5xBipolar_50us",
"name":
"BPAE_5xBipolar_50us",
"schemaKey":
"Session",
"startDate":
"2021-11-06T17:20:52-04:00"
},
{
"description":
"Metadata generated by DANDI cli",
"endDate":
"2023-05-19T16:34:58.673396-04:00",
"id":
"urn:uuid:0bab18eb-4c04-4080-aebe-08fd8e1729ba",
"name":
"Metadata generation",
"schemaKey":
"Activity",
"startDate":
"2023-05-19T16:34:58.618973-04:00",
"wasAssociatedWith":
[
{
"identifier":
"RRID:SCR_019009",
"name":
"DANDI Command Line Interface",
"schemaKey":
"Software",
"url":
"https://github.com/dandi/dandi-cli",
"version":
"0.55.0"
}
]
}
]
},
"modified":
"2023-05-19T20:43:22.984949+00:00",
"path":
"sub-Fig4-5-Bi50us-08/sub-Fig4-5-Bi50us-08_ses-BPAE-5xBipolar-50us_image.nwb",
"size":
1868943367
},
{
"asset_id":
"8ee79dc3-bd26-4e8d-917d-ce4f0b7d7ad3",
"blob":
"c24df7d4-2c52-49f3-a423-3f82dc3ccfc1",
"created":
"2023-05-19T20:37:33.988421+00:00",
"metadata":
{
"@context":
"https://raw.githubusercontent.com/dandi/schema/master/releases/0.6.4/context.json",
"access":
[
{
"schemaKey":
"AccessRequirements",
"status":
"dandi:OpenAccess"
}
],
"approach":
[],
"blobDateModified":
"2023-05-19T15:47:00.885756-04:00",
"contentSize":
1889877729,
"contentUrl":
[
"https://api.dandiarchive.org/api/assets/8ee79dc3-bd26-4e8d-917d-ce4f0b7d7ad3/download/",
"https://dandiarchive.s3.amazonaws.com/blobs/c24/df7/c24df7d4-2c52-49f3-a423-3f82dc3ccfc1"
],
"dateModified":
"2023-05-19T16:35:03.098554-04:00",
"datePublished":
"2023-05-19T20:43:22.855593+00:00",
"digest":
{
"dandi:dandi-etag":
"d87f2f8c23cdbb5357ea50dea96595e2-29",
"dandi:sha2-256":
"1a66a4ae0960218d2982477112e6ff202e63094b2b8f87d57189ee48097e8504"
},
"encodingFormat":
"application/x-nwb",
"id":
"dandiasset:8ee79dc3-bd26-4e8d-917d-ce4f0b7d7ad3",
"identifier":
"8ee79dc3-bd26-4e8d-917d-ce4f0b7d7ad3",
"measurementTechnique":
[],
"path":
"sub-Fig4-5-Uni100us-08/sub-Fig4-5-Uni100us-08_ses-BPAE-5xUnipolar-100us_image.nwb",
"publishedBy":
{
"endDate":
"2023-05-19T20:43:22.855593+00:00",
"id":
"urn:uuid:1dfc73b8-0728-453a-8393-cb8de9dfd3f3",
"name":
"DANDI publish",
"schemaKey":
"PublishActivity",
"startDate":
"2023-05-19T20:43:22.855593+00:00",
"wasAssociatedWith":
[
{
"id":
"urn:uuid:8cd20c87-dec4-41b3-a354-608bbd2ad2e9",
"identifier":
"RRID:SCR_017571",
"name":
"DANDI API",
"schemaKey":
"Software",
"version":
"0.1.0"
}
]
},
"schemaKey":
"Asset",
"schemaVersion":
"0.6.4",
"variableMeasured":
[],
"wasAttributedTo":
[
{
"age":
{
"schemaKey":
"PropertyValue",
"unitText":
"ISO-8601 duration",
"value":
"P1D",
"valueReference":
{
"schemaKey":
"PropertyValue",
"value":
"dandi:BirthReference"
}
},
"identifier":
"Fig4_5_Uni100us_08",
"schemaKey":
"Participant",
"sex":
{
"name":
"Unknown",
"schemaKey":
"SexType"
},
"species":
{
"identifier":
"http://purl.obolibrary.org/obo/NCBITaxon_9913",
"name":
"Bos taurus - Cattle",
"schemaKey":
"SpeciesType"
}
}
],
"wasGeneratedBy":
[
{
"description":
"Cells were electroporated by a train of 5 100us unipolar pulses at 1 Hz.The electrodes were two parallel stainless-steel cylinders, 1.5 mm in diameter and 3 mm apart",
"identifier":
"BPAE_5xUnipolar_100us",
"name":
"BPAE_5xUnipolar_100us",
"schemaKey":
"Session",
"startDate":
"2021-11-20T19:23:06-05:00"
},
{
"description":
"Metadata generated by DANDI cli",
"endDate":
"2023-05-19T16:35:03.098554-04:00",
"id":
"urn:uuid:4def09e4-3e3a-4cb9-9236-2d96464961c4",
"name":
"Metadata generation",
"schemaKey":
"Activity",
"startDate":
"2023-05-19T16:35:03.045076-04:00",
"wasAssociatedWith":
[
{
"identifier":
"RRID:SCR_019009",
"name":
"DANDI Command Line Interface",
"schemaKey":
"Software",
"url":
"https://github.com/dandi/dandi-cli",
"version":
"0.55.0"
}
]
}
]
},
"modified":
"2023-05-19T20:43:22.857024+00:00",
"path":
"sub-Fig4-5-Uni100us-08/sub-Fig4-5-Uni100us-08_ses-BPAE-5xUnipolar-100us_image.nwb",
"size":
1889877729
},
{
"asset_id":
"a695bead-f3a2-4291-84d1-379f3cd7e148",
"blob":
"69b9965e-750a-4833-ae82-65ba4ca9083a",
"created":
"2023-05-19T20:38:29.368666+00:00",
"metadata":
{
"@context":
"https://raw.githubusercontent.com/dandi/schema/master/releases/0.6.4/context.json",
"access":
[
{
"schemaKey":
"AccessRequirements",
"status":
"dandi:OpenAccess"
}
],
"approach":
[],
"blobDateModified":
"2023-05-19T15:54:36.517060-04:00",
"contentSize":
1884444251,
"contentUrl":
[
"https://api.dandiarchive.org/api/assets/a695bead-f3a2-4291-84d1-379f3cd7e148/download/",
"https://dandiarchive.s3.amazonaws.com/blobs/69b/996/69b9965e-750a-4833-ae82-65ba4ca9083a"
],
"dateModified":
"2023-05-19T16:36:15.385818-04:00",
"datePublished":
"2023-05-19T20:43:22.870890+00:00",
"digest":
{
"dandi:dandi-etag":
"24393a9484716ba478e406971dade189-29",
"dandi:sha2-256":
"d11df6722f53cf6317623e12d61c52c9f767c58df75e23a9e2d6efadc2cbadf1"
},
"encodingFormat":
"application/x-nwb",
"id":
"dandiasset:a695bead-f3a2-4291-84d1-379f3cd7e148",
"identifier":
"a695bead-f3a2-4291-84d1-379f3cd7e148",
"measurementTechnique":
[],
"path":
"sub-Fig4-5-Uni100us-10/sub-Fig4-5-Uni100us-10_ses-BPAE-5xUnipolar-100us_image.nwb",
"publishedBy":
{
"endDate":
"2023-05-19T20:43:22.870890+00:00",
"id":
"urn:uuid:801ff352-10e7-4a14-a123-178d1c53a76e",
"name":
"DANDI publish",
"schemaKey":
"PublishActivity",
"startDate":
"2023-05-19T20:43:22.870890+00:00",
"wasAssociatedWith":
[
{
"id":
"urn:uuid:b674dd38-a4fc-4cd7-9ac3-3920f8df140f",
"identifier":
"RRID:SCR_017571",
"name":
"DANDI API",
"schemaKey":
"Software",
"version":
"0.1.0"
}
]
},
"schemaKey":
"Asset",
"schemaVersion":
"0.6.4",
"variableMeasured":
[],
"wasAttributedTo":
[
{
"age":
{
"schemaKey":
"PropertyValue",
"unitText":
"ISO-8601 duration",
"value":
"P1D",
"valueReference":
{
"schemaKey":
"PropertyValue",
"value":
"dandi:BirthReference"
}
},
"identifier":
"Fig4_5_Uni100us_10",
"schemaKey":
"Participant",
"sex":
{
"name":
"Unknown",
"schemaKey":
"SexType"
},
"species":
{
"identifier":
"http://purl.obolibrary.org/obo/NCBITaxon_9913",
"name":
"Bos taurus - Cattle",
"schemaKey":
"SpeciesType"
}
}
],
"wasGeneratedBy":
[
{
"description":
"Cells were electroporated by a train of 5 100us unipolar pulses at 1 Hz.The electrodes were two parallel stainless-steel cylinders, 1.5 mm in diameter and 3 mm apart",
"identifier":
"BPAE_5xUnipolar_100us",
"name":
"BPAE_5xUnipolar_100us",
"schemaKey":
"Session",
"startDate":
"2021-11-20T22:08:12-05:00"
},
{
"description":
"Metadata generated by DANDI cli",
"endDate":
"2023-05-19T16:36:15.385818-04:00",
"id":
"urn:uuid:e18e84f0-d1d9-44d7-86a5-cfe7d7c6ee86",
"name":
"Metadata generation",
"schemaKey":
"Activity",
"startDate":
"2023-05-19T16:36:15.323973-04:00",
"wasAssociatedWith":
[
{
"identifier":
"RRID:SCR_019009",
"name":
"DANDI Command Line Interface",
"schemaKey":
"Software",
"url":
"https://github.com/dandi/dandi-cli",
"version":
"0.55.0"
}
]
}
]
},
"modified":
"2023-05-19T20:43:22.872793+00:00",
"path":
"sub-Fig4-5-Uni100us-10/sub-Fig4-5-Uni100us-10_ses-BPAE-5xUnipolar-100us_image.nwb",
"size":
1884444251
},
{
"asset_id":
"efa4f501-d301-4cc2-92fc-a3a7091b0ad1",
"blob":
"347376da-4b7e-453d-941f-f0795def78a8",
"created":
"2023-05-19T20:38:34.084000+00:00",
"metadata":
{
"@context":
"https://raw.githubusercontent.com/dandi/schema/master/releases/0.6.4/context.json",
"access":
[
{
"schemaKey":
"AccessRequirements",
"status":
"dandi:OpenAccess"
}
],
"approach":
[],
"blobDateModified":
"2023-05-19T15:56:46.382030-04:00",
"contentSize":
1888604620,
"contentUrl":
[
"https://api.dandiarchive.org/api/assets/efa4f501-d301-4cc2-92fc-a3a7091b0ad1/download/",
"https://dandiarchive.s3.amazonaws.com/blobs/347/376/347376da-4b7e-453d-941f-f0795def78a8"
],
"dateModified":
"2023-05-19T16:36:21.210381-04:00",
"datePublished":
"2023-05-19T20:43:22.877341+00:00",
"digest":
{
"dandi:dandi-etag":
"509e50f2b64f226c5c502ee92e15499e-29",
"dandi:sha2-256":
"1b5a7ff07da5ebe6a74a452d7fc7321d0d0dda45333df6d5ab94260600de908c"
},
"encodingFormat":
"application/x-nwb",
"id":
"dandiasset:efa4f501-d301-4cc2-92fc-a3a7091b0ad1",
"identifier":
"efa4f501-d301-4cc2-92fc-a3a7091b0ad1",
"measurementTechnique":
[],
"path":
"sub-Fig4-5-Uni100us-12/sub-Fig4-5-Uni100us-12_ses-BPAE-5xUnipolar-100us_image.nwb",
"publishedBy":
{
"endDate":
"2023-05-19T20:43:22.877341+00:00",
"id":
"urn:uuid:a9065ce5-cc3a-46fc-b157-895040787ed9",
"name":
"DANDI publish",
"schemaKey":
"PublishActivity",
"startDate":
"2023-05-19T20:43:22.877341+00:00",
"wasAssociatedWith":
[
{
"id":
"urn:uuid:c8951fb2-68c3-4cee-ae4c-4ec317601f56",
"identifier":
"RRID:SCR_017571",
"name":
"DANDI API",
"schemaKey":
"Software",
"version":
"0.1.0"
}
]
},
"schemaKey":
"Asset",
"schemaVersion":
"0.6.4",
"variableMeasured":
[],
"wasAttributedTo":
[
{
"age":
{
"schemaKey":
"PropertyValue",
"unitText":
"ISO-8601 duration",
"value":
"P1D",
"valueReference":
{
"schemaKey":
"PropertyValue",
"value":
"dandi:BirthReference"
}
},
"identifier":
"Fig4_5_Uni100us_12",
"schemaKey":
"Participant",
"sex":
{
"name":
"Unknown",
"schemaKey":
"SexType"
},
"species":
{
"identifier":
"http://purl.obolibrary.org/obo/NCBITaxon_9913",
"name":
"Bos taurus - Cattle",
"schemaKey":
"SpeciesType"
}
}
],
"wasGeneratedBy":
[
{
"description":
"Cells were electroporated by a train of 5 100us unipolar pulses at 1 Hz.The electrodes were two parallel stainless-steel cylinders, 1.5 mm in diameter and 3 mm apart",
"identifier":
"BPAE_5xUnipolar_100us",
"name":
"BPAE_5xUnipolar_100us",
"schemaKey":
"Session",
"startDate":
"2021-11-20T22:48:10-05:00"
},
{
"description":
"Metadata generated by DANDI cli",
"endDate":
"2023-05-19T16:36:21.210381-04:00",
"id":
"urn:uuid:f43e9ce9-002d-4196-9b17-c787e672ce8d",
"name":
"Metadata generation",
"schemaKey":
"Activity",
"startDate":
"2023-05-19T16:36:21.154980-04:00",
"wasAssociatedWith":
[
{
"identifier":
"RRID:SCR_019009",
"name":
"DANDI Command Line Interface",
"schemaKey":
"Software",
"url":
"https://github.com/dandi/dandi-cli",
"version":
"0.55.0"
}
]
}
]
},
"modified":
"2023-05-19T20:43:22.878903+00:00",
"path":
"sub-Fig4-5-Uni100us-12/sub-Fig4-5-Uni100us-12_ses-BPAE-5xUnipolar-100us_image.nwb",
"size":
1888604620
},
{
"asset_id":
"4a775fd7-12d6-43a4-b225-34203ba2c921",
"blob":
"c42a0849-c131-4318-8fe5-24aa25669b55",
"created":
"2023-05-19T20:38:18.734070+00:00",
"metadata":
{
"@context":
"https://raw.githubusercontent.com/dandi/schema/master/releases/0.6.4/context.json",
"access":
[
{
"schemaKey":
"AccessRequirements",
"status":
"dandi:OpenAccess"
}
],
"approach":
[],
"blobDateModified":
"2023-05-19T16:28:30.195836-04:00",
"contentSize":
1084175888,
"contentUrl":
[
"https://api.dandiarchive.org/api/assets/4a775fd7-12d6-43a4-b225-34203ba2c921/download/",
"https://dandiarchive.s3.amazonaws.com/blobs/c42/a08/c42a0849-c131-4318-8fe5-24aa25669b55"
],
"dateModified":
"2023-05-19T16:36:40.449863-04:00",
"datePublished":
"2023-05-19T20:43:22.861447+00:00",
"digest":
{
"dandi:dandi-etag":
"975707bfb09c962b9b0757654da72b21-17",
"dandi:sha2-256":
"93ea6ca830a06768d12d2d6b082eca51d25ebe5d449afdbae9291b4b1728cb21"
},
"encodingFormat":
"application/x-nwb",
"id":
"dandiasset:4a775fd7-12d6-43a4-b225-34203ba2c921",
"identifier":
"4a775fd7-12d6-43a4-b225-34203ba2c921",
"measurementTechnique":
[],
"path":
"sub-Fig4-5-Uni1200ns-01/sub-Fig4-5-Uni1200ns-01_ses-BPAE-5xUnipolar-1200ns_image.nwb",
"publishedBy":
{
"endDate":
"2023-05-19T20:43:22.861447+00:00",
"id":
"urn:uuid:80bcff9e-5a1e-4b39-bb1e-0bcc3eaa5cac",
"name":
"DANDI publish",
"schemaKey":
"PublishActivity",
"startDate":
"2023-05-19T20:43:22.861447+00:00",
"wasAssociatedWith":
[
{
"id":
"urn:uuid:4643d0cb-b5e7-446a-b081-82837a7cf09f",
"identifier":
"RRID:SCR_017571",
"name":
"DANDI API",
"schemaKey":
"Software",
"version":
"0.1.0"
}
]
},
"schemaKey":
"Asset",
"schemaVersion":
"0.6.4",
"variableMeasured":
[],
"wasAttributedTo":
[
{
"age":
{
"schemaKey":
"PropertyValue",
"unitText":
"ISO-8601 duration",
"value":
"P1D",
"valueReference":
{
"schemaKey":
"PropertyValue",
"value":
"dandi:BirthReference"
}
},
"identifier":
"Fig4_5_Uni1200ns_01",
"schemaKey":
"Participant",
"sex":
{
"name":
"Unknown",
"schemaKey":
"SexType"
},
"species":
{
"identifier":
"http://purl.obolibrary.org/obo/NCBITaxon_9913",
"name":
"Bos taurus - Cattle",
"schemaKey":
"SpeciesType"
}
}
],
"wasGeneratedBy":
[
{
"description":
"Cells were electroporated by a train of 5 1200ns unipolar pulses at 1 Hz.The electrodes were two parallel stainless-steel cylinders, 1.5 mm in diameter and 3 mm apart",
"identifier":
"BPAE_5xUnipolar_1200ns",
"name":
"BPAE_5xUnipolar_1200ns",
"schemaKey":
"Session",
"startDate":
"2021-09-01T16:54:44-04:00"
},
{
"description":
"Metadata generated by DANDI cli",
"endDate":
"2023-05-19T16:36:40.449863-04:00",
"id":
"urn:uuid:13e8f6f8-8466-4d66-9713-f251116945f6",
"name":
"Metadata generation",
"schemaKey":
"Activity",
"startDate":
"2023-05-19T16:36:40.391323-04:00",
"wasAssociatedWith":
[
{
"identifier":
"RRID:SCR_019009",
"name":
"DANDI Command Line Interface",
"schemaKey":
"Software",
"url":
"https://github.com/dandi/dandi-cli",
"version":
"0.55.0"
}
]
}
]
},
"modified":
"2023-05-19T20:43:22.863042+00:00",
"path":
"sub-Fig4-5-Uni1200ns-01/sub-Fig4-5-Uni1200ns-01_ses-BPAE-5xUnipolar-1200ns_image.nwb",
"size":
1084175888
},
{
"asset_id":
"a5fa1c70-a8b9-49f2-a4e9-d24ca356b173",
"blob":
"aa25e6da-6fee-4f2e-9283-f0f922b2f6c0",
"created":
"2023-05-19T20:38:47.516702+00:00",
"metadata":
{
"@context":
"https://raw.githubusercontent.com/dandi/schema/master/releases/0.6.4/context.json",
"access":
[
{
"schemaKey":
"AccessRequirements",
"status":
"dandi:OpenAccess"
}
],
"approach":
[],
"blobDateModified":
"2023-05-19T16:24:30.660953-04:00",
"contentSize":
1077490511,
"contentUrl":
[
"https://api.dandiarchive.org/api/assets/a5fa1c70-a8b9-49f2-a4e9-d24ca356b173/download/",
"https://dandiarchive.s3.amazonaws.com/blobs/aa2/5e6/aa25e6da-6fee-4f2e-9283-f0f922b2f6c0"
],
"dateModified":
"2023-05-19T16:37:24.119504-04:00",
"datePublished":
"2023-05-19T20:43:22.883482+00:00",
"digest":
{
"dandi:dandi-etag":
"57063ecc496a661450d8f29218a861a5-17",
"dandi:sha2-256":
"4b27a2e17e4edcc4433fc2e9d7a4babc90aa57a93fcd1cb9dbd3ed2fb298f80f"
},
"encodingFormat":
"application/x-nwb",
"id":
"dandiasset:a5fa1c70-a8b9-49f2-a4e9-d24ca356b173",
"identifier":
"a5fa1c70-a8b9-49f2-a4e9-d24ca356b173",
"measurementTechnique":
[],
"path":
"sub-Fig4-5-Uni1200ns-15/sub-Fig4-5-Uni1200ns-15_ses-BPAE-5xUnipolar-1200ns_image.nwb",
"publishedBy":
{
"endDate":
"2023-05-19T20:43:22.883482+00:00",
"id":
"urn:uuid:9a48a7a6-1f47-4a0a-9636-c78e4e169542",
"name":
"DANDI publish",
"schemaKey":
"PublishActivity",
"startDate":
"2023-05-19T20:43:22.883482+00:00",
"wasAssociatedWith":
[
{
"id":
"urn:uuid:1929e332-a27f-4315-a15b-1e0703f624c5",
"identifier":
"RRID:SCR_017571",
"name":
"DANDI API",
"schemaKey":
"Software",
"version":
"0.1.0"
}
]
},
"schemaKey":
"Asset",
"schemaVersion":
"0.6.4",
"variableMeasured":
[],
"wasAttributedTo":
[
{
"age":
{
"schemaKey":
"PropertyValue",
"unitText":
"ISO-8601 duration",
"value":
"P1D",
"valueReference":
{
"schemaKey":
"PropertyValue",
"value":
"dandi:BirthReference"
}
},
"identifier":
"Fig4_5_Uni1200ns_15",
"schemaKey":
"Participant",
"sex":
{
"name":
"Unknown",
"schemaKey":
"SexType"
},
"species":
{
"identifier":
"http://purl.obolibrary.org/obo/NCBITaxon_9913",
"name":
"Bos taurus - Cattle",
"schemaKey":
"SpeciesType"
}
}
],
"wasGeneratedBy":
[
{
"description":
"Cells were electroporated by a train of 5 1200ns unipolar pulses at 1 Hz.The electrodes were two parallel stainless-steel cylinders, 1.5 mm in diameter and 3 mm apart",
"identifier":
"BPAE_5xUnipolar_1200ns",
"name":
"BPAE_5xUnipolar_1200ns",
"schemaKey":
"Session",
"startDate":
"2021-09-01T20:43:09-04:00"
},
{
"description":
"Metadata generated by DANDI cli",
"endDate":
"2023-05-19T16:37:24.119504-04:00",
"id":
"urn:uuid:db0ba26e-046d-4abc-bcfa-80965f9be4fb",
"name":
"Metadata generation",
"schemaKey":
"Activity",
"startDate":
"2023-05-19T16:37:24.069415-04:00",
"wasAssociatedWith":
[
{
"identifier":
"RRID:SCR_019009",
"name":
"DANDI Command Line Interface",
"schemaKey":
"Software",
"url":
"https://github.com/dandi/dandi-cli",
"version":
"0.55.0"
}
]
}
]
},
"modified":
"2023-05-19T20:43:22.885110+00:00",
"path":
"sub-Fig4-5-Uni1200ns-15/sub-Fig4-5-Uni1200ns-15_ses-BPAE-5xUnipolar-1200ns_image.nwb",
"size":
1077490511
},
{
"asset_id":
"78d78feb-331a-448c-8991-f31ac02d3052",
"blob":
"a1cbac17-3b0e-4fd2-a393-d428e35150cd",
"created":
"2023-05-19T20:38:55.131319+00:00",
"metadata":
{
"@context":
"https://raw.githubusercontent.com/dandi/schema/master/releases/0.6.4/context.json",
"access":
[
{
"schemaKey":
"AccessRequirements",
"status":
"dandi:OpenAccess"
}
],
"approach":
[],
"blobDateModified":
"2023-05-19T16:00:50.458379-04:00",
"contentSize":
989266010,
"contentUrl":
[
"https://api.dandiarchive.org/api/assets/78d78feb-331a-448c-8991-f31ac02d3052/download/",
"https://dandiarchive.s3.amazonaws.com/blobs/a1c/bac/a1cbac17-3b0e-4fd2-a393-d428e35150cd"
],
"dateModified":
"2023-05-19T16:37:39.062676-04:00",
"datePublished":
"2023-05-19T20:43:22.889835+00:00",
"digest":
{
"dandi:dandi-etag":
"4464a270151d3d8c54139193588a63e8-15",
"dandi:sha2-256":
"1b444a8911c8799aa02ca6b2b72d6205aaeef6ae1f250c596ac1fc3204178f88"
},
"encodingFormat":
"application/x-nwb",
"id":
"dandiasset:78d78feb-331a-448c-8991-f31ac02d3052",
"identifier":
"78d78feb-331a-448c-8991-f31ac02d3052",
"measurementTechnique":
[],
"path":
"sub-Fig4-5-Uni300ns-01/sub-Fig4-5-Uni300ns-01_ses-BPAE-5xUnipolar-300ns_image.nwb",
"publishedBy":
{
"endDate":
"2023-05-19T20:43:22.889835+00:00",
"id":
"urn:uuid:a2ee36e2-6b6c-467b-bb82-897298760ca4",
"name":
"DANDI publish",
"schemaKey":
"PublishActivity",
"startDate":
"2023-05-19T20:43:22.889835+00:00",
"wasAssociatedWith":
[
{
"id":
"urn:uuid:7f629db2-23e4-437e-8a5a-4a2a611e9022",
"identifier":
"RRID:SCR_017571",
"name":
"DANDI API",
"schemaKey":
"Software",
"version":
"0.1.0"
}
]
},
"schemaKey":
"Asset",
"schemaVersion":
"0.6.4",
"variableMeasured":
[],
"wasAttributedTo":
[
{
"age":
{
"schemaKey":
"PropertyValue",
"unitText":
"ISO-8601 duration",
"value":
"P1D",
"valueReference":
{
"schemaKey":
"PropertyValue",
"value":
"dandi:BirthReference"
}
},
"identifier":
"Fig4_5_Uni300ns_01",
"schemaKey":
"Participant",
"sex":
{
"name":
"Unknown",
"schemaKey":
"SexType"
},
"species":
{
"identifier":
"http://purl.obolibrary.org/obo/NCBITaxon_9913",
"name":
"Bos taurus - Cattle",
"schemaKey":
"SpeciesType"
}
}
],
"wasGeneratedBy":
[
{
"description":
"Cells were electroporated by a train of 5 300ns unipolar pulses at 1 Hz.The electrodes were two parallel stainless-steel cylinders, 1.5 mm in diameter and 3 mm apart",
"identifier":
"BPAE_5xUnipolar_300ns",
"name":
"BPAE_5xUnipolar_300ns",
"schemaKey":
"Session",
"startDate":
"2021-08-14T14:35:35-04:00"
},
{
"description":
"Metadata generated by DANDI cli",
"endDate":
"2023-05-19T16:37:39.062676-04:00",
"id":
"urn:uuid:a872581b-fbcf-4e6a-ab11-ff024dff7d4c",
"name":
"Metadata generation",
"schemaKey":
"Activity",
"startDate":
"2023-05-19T16:37:39.008298-04:00",
"wasAssociatedWith":
[
{
"identifier":
"RRID:SCR_019009",
"name":
"DANDI Command Line Interface",
"schemaKey":
"Software",
"url":
"https://github.com/dandi/dandi-cli",
"version":
"0.55.0"
}
]
}
]
},
"modified":
"2023-05-19T20:43:22.891617+00:00",
"path":
"sub-Fig4-5-Uni300ns-01/sub-Fig4-5-Uni300ns-01_ses-BPAE-5xUnipolar-300ns_image.nwb",
"size":
989266010
},
{
"asset_id":
"4e24d336-36d4-4626-b7ef-bc71262378f9",
"blob":
"215158e6-a94f-46b2-b0fb-3736ca892828",
"created":
"2023-05-19T20:39:26.599688+00:00",
"metadata":
{
"@context":
"https://raw.githubusercontent.com/dandi/schema/master/releases/0.6.4/context.json",
"access":
[
{
"schemaKey":
"AccessRequirements",
"status":
"dandi:OpenAccess"
}
],
"approach":
[],
"blobDateModified":
"2023-05-19T16:02:44.539749-04:00",
"contentSize":
1023164148,
"contentUrl":
[
"https://api.dandiarchive.org/api/assets/4e24d336-36d4-4626-b7ef-bc71262378f9/download/",
"https://dandiarchive.s3.amazonaws.com/blobs/215/158/215158e6-a94f-46b2-b0fb-3736ca892828"
],
"dateModified":
"2023-05-19T16:38:23.778089-04:00",
"datePublished":
"2023-05-19T20:43:22.897021+00:00",
"digest":
{
"dandi:dandi-etag":
"5ab94e0c1ee751525f4a886d8074e6ff-16",
"dandi:sha2-256":
"8715532db5907860ebcf7285f590cc900ba370a4c3510e72a18bd5aeb68cfb62"
},
"encodingFormat":
"application/x-nwb",
"id":
"dandiasset:4e24d336-36d4-4626-b7ef-bc71262378f9",
"identifier":
"4e24d336-36d4-4626-b7ef-bc71262378f9",
"measurementTechnique":
[],
"path":
"sub-Fig4-5-Uni300ns-09/sub-Fig4-5-Uni300ns-09_ses-BPAE-5xUnipolar-300ns_image.nwb",
"publishedBy":
{
"endDate":
"2023-05-19T20:43:22.897021+00:00",
"id":
"urn:uuid:83d2b4e2-3971-4e7c-b6f9-ea9dcf63d87f",
"name":
"DANDI publish",
"schemaKey":
"PublishActivity",
"startDate":
"2023-05-19T20:43:22.897021+00:00",
"wasAssociatedWith":
[
{
"id":
"urn:uuid:7b14bf33-70df-43cb-b327-c0b2c57feb17",
"identifier":
"RRID:SCR_017571",
"name":
"DANDI API",
"schemaKey":
"Software",
"version":
"0.1.0"
}
]
},
"schemaKey":
"Asset",
"schemaVersion":
"0.6.4",
"variableMeasured":
[],
"wasAttributedTo":
[
{
"age":
{
"schemaKey":
"PropertyValue",
"unitText":
"ISO-8601 duration",
"value":
"P1D",
"valueReference":
{
"schemaKey":
"PropertyValue",
"value":
"dandi:BirthReference"
}
},
"identifier":
"Fig4_5_Uni300ns_09",
"schemaKey":
"Participant",
"sex":
{
"name":
"Unknown",
"schemaKey":
"SexType"
},
"species":
{
"identifier":
"http://purl.obolibrary.org/obo/NCBITaxon_9913",
"name":
"Bos taurus - Cattle",
"schemaKey":
"SpeciesType"
}
}
],
"wasGeneratedBy":
[
{
"description":
"Cells were electroporated by a train of 5 300ns unipolar pulses at 1 Hz.The electrodes were two parallel stainless-steel cylinders, 1.5 mm in diameter and 3 mm apart",
"identifier":
"BPAE_5xUnipolar_300ns",
"name":
"BPAE_5xUnipolar_300ns",
"schemaKey":
"Session",
"startDate":
"2021-08-14T16:30:24-04:00"
},
{
"description":
"Metadata generated by DANDI cli",
"endDate":
"2023-05-19T16:38:23.778089-04:00",
"id":
"urn:uuid:1137c881-8799-4d8e-938b-583db8ca3c6d",
"name":
"Metadata generation",
"schemaKey":
"Activity",
"startDate":
"2023-05-19T16:38:23.726208-04:00",
"wasAssociatedWith":
[
{
"identifier":
"RRID:SCR_019009",
"name":
"DANDI Command Line Interface",
"schemaKey":
"Software",
"url":
"https://github.com/dandi/dandi-cli",
"version":
"0.55.0"
}
]
}
]
},
"modified":
"2023-05-19T20:43:22.898629+00:00",
"path":
"sub-Fig4-5-Uni300ns-09/sub-Fig4-5-Uni300ns-09_ses-BPAE-5xUnipolar-300ns_image.nwb",
"size":
1023164148
},
{
"asset_id":
"47ff9f6e-7e9c-4c99-85c8-5f851b93586e",
"blob":
"b267038b-251e-4fd8-9ac8-fd51361399b2",
"created":
"2023-05-19T20:39:54.447765+00:00",
"metadata":
{
"@context":
"https://raw.githubusercontent.com/dandi/schema/master/releases/0.6.4/context.json",
"access":
[
{
"schemaKey":
"AccessRequirements",
"status":
"dandi:OpenAccess"
}
],
"approach":
[],
"blobDateModified":
"2023-05-19T16:05:12.820285-04:00",
"contentSize":
1024947134,
"contentUrl":
[
"https://api.dandiarchive.org/api/assets/47ff9f6e-7e9c-4c99-85c8-5f851b93586e/download/",
"https://dandiarchive.s3.amazonaws.com/blobs/b26/703/b267038b-251e-4fd8-9ac8-fd51361399b2"
],
"dateModified":
"2023-05-19T16:38:36.149622-04:00",
"datePublished":
"2023-05-19T20:43:22.948482+00:00",
"digest":
{
"dandi:dandi-etag":
"5d8eed3855f521daa3ce460a76c26301-16",
"dandi:sha2-256":
"c92fa4953a5945e07153a274120a711e27e6070832c16cf5499eeeaaf29455de"
},
"encodingFormat":
"application/x-nwb",
"id":
"dandiasset:47ff9f6e-7e9c-4c99-85c8-5f851b93586e",
"identifier":
"47ff9f6e-7e9c-4c99-85c8-5f851b93586e",
"measurementTechnique":
[],
"path":
"sub-Fig4-5-Uni300ns-16/sub-Fig4-5-Uni300ns-16_ses-BPAE-5xUnipolar-300ns_image.nwb",
"publishedBy":
{
"endDate":
"2023-05-19T20:43:22.948482+00:00",
"id":
"urn:uuid:5b376f38-8588-4ee6-b2b2-d622da34133a",
"name":
"DANDI publish",
"schemaKey":
"PublishActivity",
"startDate":
"2023-05-19T20:43:22.948482+00:00",
"wasAssociatedWith":
[
{
"id":
"urn:uuid:0f8c7fe0-b2d5-4da0-bc13-48d7abe1a261",
"identifier":
"RRID:SCR_017571",
"name":
"DANDI API",
"schemaKey":
"Software",
"version":
"0.1.0"
}
]
},
"schemaKey":
"Asset",
"schemaVersion":
"0.6.4",
"variableMeasured":
[],
"wasAttributedTo":
[
{
"age":
{
"schemaKey":
"PropertyValue",
"unitText":
"ISO-8601 duration",
"value":
"P1D",
"valueReference":
{
"schemaKey":
"PropertyValue",
"value":
"dandi:BirthReference"
}
},
"identifier":
"Fig4_5_Uni300ns_16",
"schemaKey":
"Participant",
"sex":
{
"name":
"Unknown",
"schemaKey":
"SexType"
},
"species":
{
"identifier":
"http://purl.obolibrary.org/obo/NCBITaxon_9913",
"name":
"Bos taurus - Cattle",
"schemaKey":
"SpeciesType"
}
}
],
"wasGeneratedBy":
[
{
"description":
"Cells were electroporated by a train of 5 300ns unipolar pulses at 1 Hz.The electrodes were two parallel stainless-steel cylinders, 1.5 mm in diameter and 3 mm apart",
"identifier":
"BPAE_5xUnipolar_300ns",
"name":
"BPAE_5xUnipolar_300ns",
"schemaKey":
"Session",
"startDate":
"2021-08-14T18:12:15-04:00"
},
{
"description":
"Metadata generated by DANDI cli",
"endDate":
"2023-05-19T16:38:36.149622-04:00",
"id":
"urn:uuid:77ed6aae-5536-4624-9cb0-134c4edbf95f",
"name":
"Metadata generation",
"schemaKey":
"Activity",
"startDate":
"2023-05-19T16:38:36.097246-04:00",
"wasAssociatedWith":
[
{
"identifier":
"RRID:SCR_019009",
"name":
"DANDI Command Line Interface",
"schemaKey":
"Software",
"url":
"https://github.com/dandi/dandi-cli",
"version":
"0.55.0"
}
]
}
]
},
"modified":
"2023-05-19T20:43:22.950268+00:00",
"path":
"sub-Fig4-5-Uni300ns-16/sub-Fig4-5-Uni300ns-16_ses-BPAE-5xUnipolar-300ns_image.nwb",
"size":
1024947134
},
{
"asset_id":
"c82ed352-c706-47ad-9dd6-e29dcec46424",
"blob":
"2b20480e-cf47-406f-91d8-f840401d6c5c",
"created":
"2023-05-19T20:41:02.548216+00:00",
"metadata":
{
"@context":
"https://raw.githubusercontent.com/dandi/schema/master/releases/0.6.4/context.json",
"access":
[
{
"schemaKey":
"AccessRequirements",
"status":
"dandi:OpenAccess"
}
],
"approach":
[],
"blobDateModified":
"2023-05-19T16:15:04.025381-04:00",
"contentSize":
1896579006,
"contentUrl":
[
"https://api.dandiarchive.org/api/assets/c82ed352-c706-47ad-9dd6-e29dcec46424/download/",
"https://dandiarchive.s3.amazonaws.com/blobs/2b2/048/2b20480e-cf47-406f-91d8-f840401d6c5c"
],
"dateModified":
"2023-05-19T16:38:42.168860-04:00",
"datePublished":
"2023-05-19T20:43:22.989995+00:00",
"digest":
{
"dandi:dandi-etag":
"51e2882b2ebb226a76d9ad61ea422a2e-29",
"dandi:sha2-256":
"03cb02d8bbc935d3320318dbabfe0344ce40017775f19ff6758e6b2f9462b0ab"
},
"encodingFormat":
"application/x-nwb",
"id":
"dandiasset:c82ed352-c706-47ad-9dd6-e29dcec46424",
"identifier":
"c82ed352-c706-47ad-9dd6-e29dcec46424",
"measurementTechnique":
[],
"path":
"sub-Fig4-5-Uni500us-07/sub-Fig4-5-Uni500us-07_ses-BPAE-5xUnipolar-500us_image.nwb",
"publishedBy":
{
"endDate":
"2023-05-19T20:43:22.989995+00:00",
"id":
"urn:uuid:2054e2fe-d027-4c80-ad6a-7ba16242486d",
"name":
"DANDI publish",
"schemaKey":
"PublishActivity",
"startDate":
"2023-05-19T20:43:22.989995+00:00",
"wasAssociatedWith":
[
{
"id":
"urn:uuid:ba1469bc-3d9f-4b24-9f11-e65d7f3dd710",
"identifier":
"RRID:SCR_017571",
"name":
"DANDI API",
"schemaKey":
"Software",
"version":
"0.1.0"
}
]
},
"schemaKey":
"Asset",
"schemaVersion":
"0.6.4",
"variableMeasured":
[],
"wasAttributedTo":
[
{
"age":
{
"schemaKey":
"PropertyValue",
"unitText":
"ISO-8601 duration",
"value":
"P1D",
"valueReference":
{
"schemaKey":
"PropertyValue",
"value":
"dandi:BirthReference"
}
},
"identifier":
"Fig4_5_Uni500us_07",
"schemaKey":
"Participant",
"sex":
{
"name":
"Unknown",
"schemaKey":
"SexType"
},
"species":
{
"identifier":
"http://purl.obolibrary.org/obo/NCBITaxon_9913",
"name":
"Bos taurus - Cattle",
"schemaKey":
"SpeciesType"
}
}
],
"wasGeneratedBy":
[
{
"description":
"Cells were electroporated by a train of 5 500us unipolar pulses at 1 Hz.The electrodes were two parallel stainless-steel cylinders, 1.5 mm in diameter and 3 mm apart",
"identifier":
"BPAE_5xUnipolar_500us",
"name":
"BPAE_5xUnipolar_500us",
"schemaKey":
"Session",
"startDate":
"2021-12-04T18:19:31-05:00"
},
{
"description":
"Metadata generated by DANDI cli",
"endDate":
"2023-05-19T16:38:42.168860-04:00",
"id":
"urn:uuid:ccfd0118-8df9-4084-ab5d-23a6f9f48d8d",
"name":
"Metadata generation",
"schemaKey":
"Activity",
"startDate":
"2023-05-19T16:38:42.115426-04:00",
"wasAssociatedWith":
[
{
"identifier":
"RRID:SCR_019009",
"name":
"DANDI Command Line Interface",
"schemaKey":
"Software",
"url":
"https://github.com/dandi/dandi-cli",
"version":
"0.55.0"
}
]
}
]
},
"modified":
"2023-05-19T20:43:22.991544+00:00",
"path":
"sub-Fig4-5-Uni500us-07/sub-Fig4-5-Uni500us-07_ses-BPAE-5xUnipolar-500us_image.nwb",
"size":
1896579006
},
{
"asset_id":
"892a3851-379c-4770-bf32-d122b1fbf2bc",
"blob":
"e6ef995a-e255-46cc-a3ee-b672a65a970a",
"created":
"2023-05-19T20:41:21.107452+00:00",
"metadata":
{
"@context":
"https://raw.githubusercontent.com/dandi/schema/master/releases/0.6.4/context.json",
"access":
[
{
"schemaKey":
"AccessRequirements",
"status":
"dandi:OpenAccess"
}
],
"approach":
[],
"blobDateModified":
"2023-05-19T16:17:24.687736-04:00",
"contentSize":
1889351194,
"contentUrl":
[
"https://api.dandiarchive.org/api/assets/892a3851-379c-4770-bf32-d122b1fbf2bc/download/",
"https://dandiarchive.s3.amazonaws.com/blobs/e6e/f99/e6ef995a-e255-46cc-a3ee-b672a65a970a"
],
"dateModified":
"2023-05-19T16:38:55.708947-04:00",
"datePublished":
"2023-05-19T20:43:22.996697+00:00",
"digest":
{
"dandi:dandi-etag":
"9e7b3438a4bfdcbd9290df5432e2ce5f-29",
"dandi:sha2-256":
"8cc1384f8efa928653cd43942c549a4b4f35a5302d73257b498350a36c4bbfd8"
},
"encodingFormat":
"application/x-nwb",
"id":
"dandiasset:892a3851-379c-4770-bf32-d122b1fbf2bc",
"identifier":
"892a3851-379c-4770-bf32-d122b1fbf2bc",
"measurementTechnique":
[],
"path":
"sub-Fig4-5-Uni500us-09/sub-Fig4-5-Uni500us-09_ses-BPAE-5xUnipolar-500us_image.nwb",
"publishedBy":
{
"endDate":
"2023-05-19T20:43:22.996697+00:00",
"id":
"urn:uuid:1ecb6e05-398b-4b98-b50d-1e3e9f857553",
"name":
"DANDI publish",
"schemaKey":
"PublishActivity",
"startDate":
"2023-05-19T20:43:22.996697+00:00",
"wasAssociatedWith":
[
{
"id":
"urn:uuid:4bf9823d-6d5e-4677-9b2a-c0d9f3e1fad1",
"identifier":
"RRID:SCR_017571",
"name":
"DANDI API",
"schemaKey":
"Software",
"version":
"0.1.0"
}
]
},
"schemaKey":
"Asset",
"schemaVersion":
"0.6.4",
"variableMeasured":
[],
"wasAttributedTo":
[
{
"age":
{
"schemaKey":
"PropertyValue",
"unitText":
"ISO-8601 duration",
"value":
"P1D",
"valueReference":
{
"schemaKey":
"PropertyValue",
"value":
"dandi:BirthReference"
}
},
"identifier":
"Fig4_5_Uni500us_09",
"schemaKey":
"Participant",
"sex":
{
"name":
"Unknown",
"schemaKey":
"SexType"
},
"species":
{
"identifier":
"http://purl.obolibrary.org/obo/NCBITaxon_9913",
"name":
"Bos taurus - Cattle",
"schemaKey":
"SpeciesType"
}
}
],
"wasGeneratedBy":
[
{
"description":
"Cells were electroporated by a train of 5 500us unipolar pulses at 1 Hz.The electrodes were two parallel stainless-steel cylinders, 1.5 mm in diameter and 3 mm apart",
"identifier":
"BPAE_5xUnipolar_500us",
"name":
"BPAE_5xUnipolar_500us",
"schemaKey":
"Session",
"startDate":
"2021-12-04T18:58:55-05:00"
},
{
"description":
"Metadata generated by DANDI cli",
"endDate":
"2023-05-19T16:38:55.708947-04:00",
"id":
"urn:uuid:43e57f88-143d-4a99-8c93-72617ae4d03c",
"name":
"Metadata generation",
"schemaKey":
"Activity",
"startDate":
"2023-05-19T16:38:55.653131-04:00",
"wasAssociatedWith":
[
{
"identifier":
"RRID:SCR_019009",
"name":
"DANDI Command Line Interface",
"schemaKey":
"Software",
"url":
"https://github.com/dandi/dandi-cli",
"version":
"0.55.0"
}
]
}
]
},
"modified":
"2023-05-19T20:43:22.998288+00:00",
"path":
"sub-Fig4-5-Uni500us-09/sub-Fig4-5-Uni500us-09_ses-BPAE-5xUnipolar-500us_image.nwb",
"size":
1889351194
},
{
"asset_id":
"60353c0c-4806-405c-82f5-e0ca13588f92",
"blob":
"be133ab6-5262-408f-84af-6839f3ab572e",
"created":
"2023-05-19T20:41:26.483551+00:00",
"metadata":
{
"@context":
"https://raw.githubusercontent.com/dandi/schema/master/releases/0.6.4/context.json",
"access":
[
{
"schemaKey":
"AccessRequirements",
"status":
"dandi:OpenAccess"
}
],
"approach":
[],
"blobDateModified":
"2023-05-19T15:27:32.658797-04:00",
"contentSize":
1868438895,
"contentUrl":
[
"https://api.dandiarchive.org/api/assets/60353c0c-4806-405c-82f5-e0ca13588f92/download/",
"https://dandiarchive.s3.amazonaws.com/blobs/be1/33a/be133ab6-5262-408f-84af-6839f3ab572e"
],
"dateModified":
"2023-05-19T16:39:03.431762-04:00",
"datePublished":
"2023-05-19T20:43:22.903499+00:00",
"digest":
{
"dandi:dandi-etag":
"bf989f29fc2ec4b686612b9dbf198fbb-28",
"dandi:sha2-256":
"b3fec4a5e7fd924aa1f37127a42591cf7acb029e4c5acba035112f570b07bd15"
},
"encodingFormat":
"application/x-nwb",
"id":
"dandiasset:60353c0c-4806-405c-82f5-e0ca13588f92",
"identifier":
"60353c0c-4806-405c-82f5-e0ca13588f92",
"measurementTechnique":
[],
"path":
"sub-Fig4-5-Uni50us-03/sub-Fig4-5-Uni50us-03_ses-BPAE-5xUnipolar-50us_obj-o92bhj_image.nwb",
"publishedBy":
{
"endDate":
"2023-05-19T20:43:22.903499+00:00",
"id":
"urn:uuid:e020c171-e6b7-4649-9ebf-9d8da3af1bd4",
"name":
"DANDI publish",
"schemaKey":
"PublishActivity",
"startDate":
"2023-05-19T20:43:22.903499+00:00",
"wasAssociatedWith":
[
{
"id":
"urn:uuid:da4efdaf-cdee-41e2-93fc-98b77403a6c9",
"identifier":
"RRID:SCR_017571",
"name":
"DANDI API",
"schemaKey":
"Software",
"version":
"0.1.0"
}
]
},
"schemaKey":
"Asset",
"schemaVersion":
"0.6.4",
"variableMeasured":
[],
"wasAttributedTo":
[
{
"age":
{
"schemaKey":
"PropertyValue",
"unitText":
"ISO-8601 duration",
"value":
"P1D",
"valueReference":
{
"schemaKey":
"PropertyValue",
"value":
"dandi:BirthReference"
}
},
"identifier":
"Fig4_5_Uni50us_03",
"schemaKey":
"Participant",
"sex":
{
"name":
"Unknown",
"schemaKey":
"SexType"
},
"species":
{
"identifier":
"http://purl.obolibrary.org/obo/NCBITaxon_9913",
"name":
"Bos taurus - Cattle",
"schemaKey":
"SpeciesType"
}
}
],
"wasGeneratedBy":
[
{
"description":
"Cells were electroporated by a train of 5 50us unipolar pulses at 1 Hz.The electrodes were two parallel stainless-steel cylinders, 1.5 mm in diameter and 3 mm apart",
"identifier":
"BPAE_5xUnipolar_50us",
"name":
"BPAE_5xUnipolar_50us",
"schemaKey":
"Session",
"startDate":
"2021-11-06T15:36:10-04:00"
},
{
"description":
"Metadata generated by DANDI cli",
"endDate":
"2023-05-19T16:39:03.431762-04:00",
"id":
"urn:uuid:11e1fb39-55be-4290-bfb5-f71ca8e744a3",
"name":
"Metadata generation",
"schemaKey":
"Activity",
"startDate":
"2023-05-19T16:39:03.376704-04:00",
"wasAssociatedWith":
[
{
"identifier":
"RRID:SCR_019009",
"name":
"DANDI Command Line Interface",
"schemaKey":
"Software",
"url":
"https://github.com/dandi/dandi-cli",
"version":
"0.55.0"
}
]
}
]
},
"modified":
"2023-05-19T20:43:22.905124+00:00",
"path":
"sub-Fig4-5-Uni50us-03/sub-Fig4-5-Uni50us-03_ses-BPAE-5xUnipolar-50us_obj-o92bhj_image.nwb",
"size":
1868438895
},
{
"asset_id":
"95a6bf73-f541-4d61-aabf-427b49d443db",
"blob":
"bcd87427-42aa-4e00-b23a-1f896e91e21f",
"created":
"2023-05-19T20:41:39.183053+00:00",
"metadata":
{
"@context":
"https://raw.githubusercontent.com/dandi/schema/master/releases/0.6.4/context.json",
"access":
[
{
"schemaKey":
"AccessRequirements",
"status":
"dandi:OpenAccess"
}
],
"approach":
[],
"blobDateModified":
"2023-05-19T15:29:24.466340-04:00",
"contentSize":
1868438895,
"contentUrl":
[
"https://api.dandiarchive.org/api/assets/95a6bf73-f541-4d61-aabf-427b49d443db/download/",
"https://dandiarchive.s3.amazonaws.com/blobs/bcd/874/bcd87427-42aa-4e00-b23a-1f896e91e21f"
],
"dateModified":
"2023-05-19T16:39:34.942487-04:00",
"datePublished":
"2023-05-19T20:43:22.962375+00:00",
"digest":
{
"dandi:dandi-etag":
"bf2e19f90994b84fc492f2ef3aeff551-28",
"dandi:sha2-256":
"f88109f1252a228604795205d845954ba16f7b6bb26eb6dbcaa86a08a3f22b3e"
},
"encodingFormat":
"application/x-nwb",
"id":
"dandiasset:95a6bf73-f541-4d61-aabf-427b49d443db",
"identifier":
"95a6bf73-f541-4d61-aabf-427b49d443db",
"measurementTechnique":
[],
"path":
"sub-Fig4-5-Uni50us-03/sub-Fig4-5-Uni50us-03_ses-BPAE-5xUnipolar-50us_obj-wlwhic_image.nwb",
"publishedBy":
{
"endDate":
"2023-05-19T20:43:22.962375+00:00",
"id":
"urn:uuid:6387ecef-0b66-497a-be07-2bba284f2e9d",
"name":
"DANDI publish",
"schemaKey":
"PublishActivity",
"startDate":
"2023-05-19T20:43:22.962375+00:00",
"wasAssociatedWith":
[
{
"id":
"urn:uuid:271ccd7a-ea32-45df-9036-8e2cda5bb5c6",
"identifier":
"RRID:SCR_017571",
"name":
"DANDI API",
"schemaKey":
"Software",
"version":
"0.1.0"
}
]
},
"schemaKey":
"Asset",
"schemaVersion":
"0.6.4",
"variableMeasured":
[],
"wasAttributedTo":
[
{
"age":
{
"schemaKey":
"PropertyValue",
"unitText":
"ISO-8601 duration",
"value":
"P1D",
"valueReference":
{
"schemaKey":
"PropertyValue",
"value":
"dandi:BirthReference"
}
},
"identifier":
"Fig4_5_Uni50us_03",
"schemaKey":
"Participant",
"sex":
{
"name":
"Unknown",
"schemaKey":
"SexType"
},
"species":
{
"identifier":
"http://purl.obolibrary.org/obo/NCBITaxon_9913",
"name":
"Bos taurus - Cattle",
"schemaKey":
"SpeciesType"
}
}
],
"wasGeneratedBy":
[
{
"description":
"Cells were electroporated by a train of 5 50us unipolar pulses at 1 Hz.The electrodes were two parallel stainless-steel cylinders, 1.5 mm in diameter and 3 mm apart",
"identifier":
"BPAE_5xUnipolar_50us",
"name":
"BPAE_5xUnipolar_50us",
"schemaKey":
"Session",
"startDate":
"2021-11-06T15:36:10-04:00"
},
{
"description":
"Metadata generated by DANDI cli",
"endDate":
"2023-05-19T16:39:34.942487-04:00",
"id":
"urn:uuid:31ddad90-fcd9-4d47-998b-44424b80b3a5",
"name":
"Metadata generation",
"schemaKey":
"Activity",
"startDate":
"2023-05-19T16:39:34.889466-04:00",
"wasAssociatedWith":
[
{
"identifier":
"RRID:SCR_019009",
"name":
"DANDI Command Line Interface",
"schemaKey":
"Software",
"url":
"https://github.com/dandi/dandi-cli",
"version":
"0.55.0"
}
]
}
]
},
"modified":
"2023-05-19T20:43:22.967351+00:00",
"path":
"sub-Fig4-5-Uni50us-03/sub-Fig4-5-Uni50us-03_ses-BPAE-5xUnipolar-50us_obj-wlwhic_image.nwb",
"size":
1868438895
},
{
"asset_id":
"55ac80b2-5b25-4033-bbcb-2457b7c05d79",
"blob":
"23b0bf08-5f9a-4a1e-b7e0-41155eea6ba8",
"created":
"2023-05-19T20:41:43.929135+00:00",
"metadata":
{
"@context":
"https://raw.githubusercontent.com/dandi/schema/master/releases/0.6.4/context.json",
"access":
[
{
"schemaKey":
"AccessRequirements",
"status":
"dandi:OpenAccess"
}
],
"approach":
[],
"blobDateModified":
"2023-05-19T15:33:38.591486-04:00",
"contentSize":
1863792481,
"contentUrl":
[
"https://api.dandiarchive.org/api/assets/55ac80b2-5b25-4033-bbcb-2457b7c05d79/download/",
"https://dandiarchive.s3.amazonaws.com/blobs/23b/0bf/23b0bf08-5f9a-4a1e-b7e0-41155eea6ba8"
],
"dateModified":
"2023-05-19T16:40:02.673849-04:00",
"datePublished":
"2023-05-19T20:43:22.909647+00:00",
"digest":
{
"dandi:dandi-etag":
"8297c50009ed88cdcacf21b0f7446caa-28",
"dandi:sha2-256":
"482a119adc563c52ff318b22d26acbdf3bb0702cb3b46e3569bc0995195c656d"
},
"encodingFormat":
"application/x-nwb",
"id":
"dandiasset:55ac80b2-5b25-4033-bbcb-2457b7c05d79",
"identifier":
"55ac80b2-5b25-4033-bbcb-2457b7c05d79",
"measurementTechnique":
[],
"path":
"sub-Fig4-5-Uni50us-05/sub-Fig4-5-Uni50us-05_ses-BPAE-5xUnipolar-50us_image.nwb",
"publishedBy":
{
"endDate":
"2023-05-19T20:43:22.909647+00:00",
"id":
"urn:uuid:0f9b5747-49e6-4aeb-a8b7-23c0971cbcfd",
"name":
"DANDI publish",
"schemaKey":
"PublishActivity",
"startDate":
"2023-05-19T20:43:22.909647+00:00",
"wasAssociatedWith":
[
{
"id":
"urn:uuid:4df3f9b7-7617-4691-98e7-8168eb7bd271",
"identifier":
"RRID:SCR_017571",
"name":
"DANDI API",
"schemaKey":
"Software",
"version":
"0.1.0"
}
]
},
"schemaKey":
"Asset",
"schemaVersion":
"0.6.4",
"variableMeasured":
[],
"wasAttributedTo":
[
{
"age":
{
"schemaKey":
"PropertyValue",
"unitText":
"ISO-8601 duration",
"value":
"P1D",
"valueReference":
{
"schemaKey":
"PropertyValue",
"value":
"dandi:BirthReference"
}
},
"identifier":
"Fig4_5_Uni50us_05",
"schemaKey":
"Participant",
"sex":
{
"name":
"Unknown",
"schemaKey":
"SexType"
},
"species":
{
"identifier":
"http://purl.obolibrary.org/obo/NCBITaxon_9913",
"name":
"Bos taurus - Cattle",
"schemaKey":
"SpeciesType"
}
}
],
"wasGeneratedBy":
[
{
"description":
"Cells were electroporated by a train of 5 50us unipolar pulses at 1 Hz.The electrodes were two parallel stainless-steel cylinders, 1.5 mm in diameter and 3 mm apart",
"identifier":
"BPAE_5xUnipolar_50us",
"name":
"BPAE_5xUnipolar_50us",
"schemaKey":
"Session",
"startDate":
"2021-11-06T16:24:29-04:00"
},
{
"description":
"Metadata generated by DANDI cli",
"endDate":
"2023-05-19T16:40:02.673849-04:00",
"id":
"urn:uuid:b4be2c01-a084-4d04-9b40-aabacc5f6309",
"name":
"Metadata generation",
"schemaKey":
"Activity",
"startDate":
"2023-05-19T16:40:02.619982-04:00",
"wasAssociatedWith":
[
{
"identifier":
"RRID:SCR_019009",
"name":
"DANDI Command Line Interface",
"schemaKey":
"Software",
"url":
"https://github.com/dandi/dandi-cli",
"version":
"0.55.0"
}
]
}
]
},
"modified":
"2023-05-19T20:43:22.911446+00:00",
"path":
"sub-Fig4-5-Uni50us-05/sub-Fig4-5-Uni50us-05_ses-BPAE-5xUnipolar-50us_image.nwb",
"size":
1863792481
}
]